{"result":{"_id":"591b37ca9e5344273dffaa78","created":"2017-05-16T17:32:58.943Z","updated":"2017-05-16T17:32:58.951Z","analysis_date":"2017-05-17T05:32:57.000Z","taxonomy_version":5,"analysis_name":"Followers of @meeshthesinger on 2017-05-17","number_submitted":15782,"number_processed":7119,"analysis_id":6916347,"request_id":32991340,"data":{"networksettings":{"websiteset":{"percent":27.7,"number":1971,"code":"X02","name":"Website set"},"geoenabled":{"percent":31.3,"number":2225,"code":"X03","name":"Geo-enabled"},"protected":{"percent":31.7,"number":2256,"code":"X05","name":"Protected"}},"postingfrequency":{"over5postsperday":{"percent":0.3,"number":19,"code":"A01","name":"> 5 posts/day"},"1to5postsperday":{"percent":8.9,"number":634,"code":"A02","name":"1-5 posts/day"},"under1postpermonth":{"percent":13.6,"number":969,"code":"A05","name":"< 1 post/month"},"1to4postspermonth":{"percent":25.9,"number":1841,"code":"A04","name":"1-4 posts/month"},"1to7postsperweek":{"percent":51,"number":3633,"code":"A03","name":"1-7 posts/week"}},"accountsfollowed":{"under10accounts":{"percent":0.1,"number":5,"code":"N24","name":"< 10 accounts"},"10to100accounts":{"percent":2.1,"number":151,"code":"N23","name":"10-100 accounts"},"over1000accounts":{"percent":31.9,"number":2272,"code":"N21","name":"> 1,000 accounts"},"101to1000accounts":{"percent":65.8,"number":4684,"code":"N22","name":"101-1,000 accounts"}},"timeonnetwork":{"under6months":{"percent":0.9,"number":66,"code":"Y05","name":"< 6 months"},"6to12months":{"percent":2.6,"number":185,"code":"Y04","name":"6-12 months"},"1to2years":{"percent":7.8,"number":557,"code":"Y03","name":"1-2 years"},"2to3years":{"percent":20.9,"number":1485,"code":"Y02","name":"2-3 years"},"over3years":{"percent":67.7,"number":4819,"code":"Y01","name":"> 3 years"}},"numberoffollowers":{"under10followers":{"percent":0.9,"number":66,"code":"I05","name":"< 10 followers"},"10to100followers":{"percent":10,"number":710,"code":"I04","name":"10-100 followers"},"over1000followers":{"percent":13.6,"number":968,"code":"I02","name":"> 1,000 followers"},"101to1000followers":{"percent":75.4,"number":5368,"code":"I03","name":"101-1,000 followers"}},"influences":{"bowwow":{"percent":5.7,"number":406,"code":"Vew","name":"Bow Wow"},"nfl":{"percent":5.7,"number":408,"code":"Vai","name":"NFL"},"nicolescherzinger":{"percent":5.8,"number":413,"code":"Vq7","name":"Nicole Scherzinger"},"charliesheen":{"percent":5.8,"number":416,"code":"V26","name":"Charlie Sheen"},"kellyrowland":{"percent":5.8,"number":414,"code":"Voe","name":"Kelly Rowland"},"lalakers":{"percent":5.8,"number":412,"code":"Vap","name":"LA Lakers"},"nickjonas":{"percent":5.9,"number":418,"code":"V56","name":"Nick Jonas"},"sammigiancola":{"percent":5.9,"number":418,"code":"Vl2","name":"Sammi Giancola"},"starbuckscoffee":{"percent":5.9,"number":419,"code":"Vd8","name":"Starbucks Coffee"},"rickross":{"percent":6.1,"number":435,"code":"VI8","name":"Rick Ross"},"emmawatson":{"percent":6.2,"number":441,"code":"Vdu","name":"Emma Watson"},"hilaryduff":{"percent":6.2,"number":443,"code":"Vu7","name":"Hilary Duff"},"espn":{"percent":6.2,"number":440,"code":"Vcs","name":"ESPN"},"parishilton":{"percent":6.3,"number":450,"code":"V28","name":"Paris Hilton"},"ti":{"percent":6.3,"number":449,"code":"VK0","name":"T.I."},"conanobrien":{"percent":6.4,"number":459,"code":"V45","name":"Conan O'Brien"},"lala":{"percent":6.6,"number":471,"code":"Vn8","name":"La La"},"sportscenter":{"percent":6.6,"number":473,"code":"Vjh","name":"SportsCenter"},"dwighthoward":{"percent":6.7,"number":475,"code":"Vaz","name":"Dwight Howard"},"ryanseacrest":{"percent":6.7,"number":479,"code":"V20","name":"Ryan Seacrest"},"laurenlondon":{"percent":7,"number":496,"code":"Vly","name":"Lauren London"},"thegame":{"percent":7,"number":499,"code":"VRY","name":"The Game"},"neyo":{"percent":7.1,"number":507,"code":"VN3","name":"Ne-Yo"},"laurenconrad":{"percent":7.1,"number":504,"code":"Vbf","name":"Lauren Conrad"},"carmeloanthony":{"percent":7.2,"number":514,"code":"Vj8","name":"Carmelo Anthony"},"oprahwinfrey":{"percent":7.3,"number":520,"code":"V11","name":"Oprah Winfrey"},"lucyhale":{"percent":7.4,"number":526,"code":"VWJ","name":"Lucy Hale"},"tyrabanks":{"percent":7.5,"number":536,"code":"V43","name":"Tyra Banks"},"mtv":{"percent":7.6,"number":538,"code":"Vcg","name":"MTV"},"fabolous":{"percent":7.7,"number":546,"code":"VJ7","name":"Fabolous"},"channingtatum":{"percent":7.7,"number":548,"code":"VRP","name":"Channing Tatum"},"floydmayweather":{"percent":7.7,"number":545,"code":"Vez","name":"Floyd Mayweather"},"wale":{"percent":7.8,"number":556,"code":"VNP","name":"Wale"},"ashtonkutcher":{"percent":7.9,"number":561,"code":"V09","name":"Ashton Kutcher"},"johnlegend":{"percent":8.3,"number":593,"code":"V89","name":"John Legend"},"kerihilson":{"percent":8.3,"number":591,"code":"Vdy","name":"Keri Hilson"},"scottdisick":{"percent":8.3,"number":588,"code":"Vxy","name":"Scott Disick"},"ashleytisdale":{"percent":8.4,"number":601,"code":"V22","name":"Ashley Tisdale"},"vinnyguadagnino":{"percent":8.4,"number":601,"code":"Vcw","name":"Vinny Guadagnino"},"robdyrdek":{"percent":8.7,"number":619,"code":"Vgi","name":"Rob Dyrdek"},"dwyanewade":{"percent":8.7,"number":622,"code":"Vdl","name":"Dwyane Wade"},"50cent":{"percent":8.7,"number":616,"code":"V25","name":"50 Cent"},"mariahcarey":{"percent":8.8,"number":627,"code":"V27","name":"Mariah Carey"},"victoriajustice":{"percent":8.8,"number":629,"code":"VKU","name":"Victoria Justice"},"jimmyfallon":{"percent":9,"number":639,"code":"V38","name":"Jimmy Fallon"},"nike":{"percent":9,"number":641,"code":"VZ3","name":"Nike"},"tyresegibson":{"percent":9.1,"number":648,"code":"Vc4","name":"Tyrese Gibson"},"britneyspears":{"percent":9.2,"number":657,"code":"V06","name":"Britney Spears"},"jennettemccurdy":{"percent":9.2,"number":653,"code":"VPL","name":"Jennette McCurdy"},"shaquilleoneal":{"percent":9.4,"number":667,"code":"V30","name":"Shaquille O'Neal"},"macmiller":{"percent":9.5,"number":679,"code":"VRU","name":"Mac Miller"},"ciara":{"percent":9.6,"number":684,"code":"Vga","name":"Ciara"},"robkardashian":{"percent":9.7,"number":688,"code":"Vc2","name":"Rob Kardashian"},"jwowwfarley":{"percent":9.7,"number":692,"code":"Vdp","name":"JWoww Farley"},"barackobama":{"percent":9.9,"number":704,"code":"V03","name":"Barack Obama"},"paulyd":{"percent":10,"number":711,"code":"Vbo","name":"Pauly D"},"ladygaga":{"percent":10.1,"number":716,"code":"V01","name":"Lady Gaga"},"kevindurant":{"percent":10.1,"number":717,"code":"Vky","name":"Kevin Durant"},"eminem":{"percent":10.5,"number":746,"code":"V17","name":"Eminem"},"jasminev":{"percent":10.6,"number":752,"code":"VN4","name":"Jasmine V."},"youtube":{"percent":10.7,"number":763,"code":"V34","name":"YouTube"},"jcole":{"percent":10.9,"number":776,"code":"VNT","name":"J. Cole"},"aliciakeys":{"percent":10.9,"number":773,"code":"V29","name":"Alicia Keys"},"revrun":{"percent":11,"number":783,"code":"V88","name":"Rev Run"},"usher":{"percent":11.1,"number":791,"code":"Vav","name":"Usher"},"snoopdogg":{"percent":11.6,"number":826,"code":"V37","name":"Snoop Dogg"},"nba":{"percent":11.6,"number":828,"code":"V71","name":"NBA"},"pdiddy":{"percent":11.8,"number":838,"code":"V39","name":"P. Diddy"},"lilwayne":{"percent":11.8,"number":843,"code":"V70","name":"Lil Wayne"},"kanyewest":{"percent":11.8,"number":840,"code":"V35","name":"Kanye West"},"jenniferlopez":{"percent":12.2,"number":872,"code":"V87","name":"Jennifer Lopez"},"mileycyrus":{"percent":12.2,"number":869,"code":"Vah","name":"Miley Cyrus"},"brunomars":{"percent":12.3,"number":878,"code":"V95","name":"Bruno Mars"},"jeremylin":{"percent":12.4,"number":886,"code":"VZX","name":"Jeremy Lin"},"lebronjames":{"percent":12.7,"number":907,"code":"Va0","name":"LeBron James"},"ludacris":{"percent":12.8,"number":909,"code":"V77","name":"Ludacris"},"demilovato":{"percent":13,"number":924,"code":"V32","name":"Demi Lovato"},"bigsean":{"percent":13.1,"number":933,"code":"VM8","name":"Big Sean"},"snookipolizzi":{"percent":13.5,"number":961,"code":"V74","name":"Snooki Polizzi"},"tyga":{"percent":13.7,"number":974,"code":"VHX","name":"Tyga"},"treysongz":{"percent":14.4,"number":1023,"code":"Vaj","name":"Trey Songz"},"beyonceknowles":{"percent":14.6,"number":1036,"code":"Ve5","name":"Beyonce Knowles"},"taylorswift":{"percent":15.5,"number":1101,"code":"V08","name":"Taylor Swift"},"ellendegeneres":{"percent":15.6,"number":1109,"code":"V10","name":"Ellen DeGeneres"},"katyperry":{"percent":15.8,"number":1127,"code":"V04","name":"Katy Perry"},"justintimberlake":{"percent":16.6,"number":1185,"code":"V16","name":"Justin Timberlake"},"therock":{"percent":17.6,"number":1251,"code":"Vju","name":"The Rock"},"khlokardashian":{"percent":17.6,"number":1254,"code":"V31","name":"Khloé Kardashian"},"kourtneykardashian":{"percent":17.7,"number":1257,"code":"V51","name":"Kourtney Kardashian"},"justinbieber":{"percent":17.7,"number":1259,"code":"V02","name":"Justin Bieber"},"wizkhalifa":{"percent":18.4,"number":1313,"code":"V79","name":"Wiz Khalifa"},"rihanna":{"percent":18.9,"number":1348,"code":"V12","name":"Rihanna"},"chrisbrown":{"percent":19.3,"number":1376,"code":"V33","name":"Chris Brown"},"nickiminaj":{"percent":19.4,"number":1380,"code":"V19","name":"Nicki Minaj"},"kendalljenner":{"percent":20.1,"number":1433,"code":"Vjt","name":"Kendall Jenner"},"selenagomez":{"percent":21.6,"number":1535,"code":"V13","name":"Selena Gomez"},"drake":{"percent":22.7,"number":1618,"code":"V66","name":"Drake"},"kimkardashian":{"percent":24.7,"number":1756,"code":"V05","name":"Kim Kardashian"},"kevinhart":{"percent":26.4,"number":1877,"code":"Vc0","name":"Kevin Hart"},"arianagrande":{"percent":26.9,"number":1913,"code":"VO4","name":"Ariana Grande"}},"brands":{"converse":{"percent":2,"number":145,"code":"Wna","name":"Converse"},"people":{"percent":2,"number":140,"code":"W4i","name":"People"},"toyota":{"percent":2,"number":139,"code":"B70","name":"Toyota"},"lexus":{"percent":2,"number":144,"code":"B67","name":"Lexus"},"walgreens":{"percent":2,"number":143,"code":"B58","name":"Walgreens"},"virginatlantic":{"percent":2.1,"number":149,"code":"M3p","name":"Virgin Atlantic"},"wholefoods":{"percent":2.1,"number":152,"code":"B60","name":"Whole Foods"},"hooters":{"percent":2.1,"number":146,"code":"Mb9","name":"Hooters"},"nintendo":{"percent":2.1,"number":152,"code":"Uab","name":"Nintendo"},"nbc":{"percent":2.1,"number":147,"code":"Wgc","name":"NBC"},"jambajuice":{"percent":2.1,"number":151,"code":"Mnc","name":"Jamba Juice"},"cocacola":{"percent":2.1,"number":147,"code":"M1l","name":"Coca Cola"},"abc":{"percent":2.1,"number":146,"code":"Wga","name":"ABC"},"nissan":{"percent":2.2,"number":158,"code":"B68","name":"Nissan"},"nordstrom":{"percent":2.2,"number":154,"code":"W47","name":"Nordstrom"},"vogue":{"percent":2.2,"number":154,"code":"W4h","name":"Vogue"},"fox":{"percent":2.2,"number":160,"code":"Wg2","name":"Fox"},"krispykreme":{"percent":2.2,"number":154,"code":"Mnd","name":"Krispy Kreme"},"panerabread":{"percent":2.3,"number":167,"code":"Mnf","name":"Panera Bread"},"chanel":{"percent":2.3,"number":164,"code":"W19","name":"Chanel"},"burberry":{"percent":2.3,"number":166,"code":"W15","name":"Burberry"},"breakingnews":{"percent":2.3,"number":167,"code":"W9v","name":"Breaking News"},"benefitcosmetics":{"percent":2.3,"number":166,"code":"B1h","name":"Benefit Cosmetics"},"bbc":{"percent":2.4,"number":170,"code":"Wfz","name":"BBC"},"callofduty":{"percent":2.4,"number":172,"code":"Uiw","name":"Call of Duty"},"dennys":{"percent":2.5,"number":180,"code":"Mbj","name":"Denny's"},"bmw":{"percent":2.5,"number":177,"code":"B00","name":"BMW"},"olivegarden":{"percent":2.5,"number":178,"code":"Maz","name":"Olive Garden"},"redbull":{"percent":2.5,"number":181,"code":"M1n","name":"Redbull"},"amcnetworks":{"percent":2.5,"number":179,"code":"Wgj","name":"AMC Networks"},"finishline":{"percent":2.5,"number":176,"code":"W28","name":"Finish Line"},"buffalowildwings":{"percent":2.5,"number":176,"code":"Mbd","name":"Buffalo Wild Wings"},"popeyes":{"percent":2.5,"number":176,"code":"Mb4","name":"Popeye's"},"applemac":{"percent":2.5,"number":175,"code":"U14","name":"Apple Mac"},"smosh":{"percent":2.6,"number":182,"code":"W9z","name":"Smosh"},"michaelkors":{"percent":2.6,"number":186,"code":"Wnp","name":"Michael Kors"},"onelouderapps":{"percent":2.7,"number":193,"code":"Udc","name":"One Louder Apps"},"nytimes":{"percent":2.7,"number":192,"code":"W00","name":"NY Times"},"wingstop":{"percent":2.7,"number":191,"code":"Mbc","name":"Wingstop"},"xbox":{"percent":2.7,"number":190,"code":"Ua9","name":"Xbox"},"innout":{"percent":2.8,"number":199,"code":"Mc3","name":"In-N-Out"},"sony":{"percent":2.8,"number":202,"code":"Ua8","name":"Sony"},"karmaloop":{"percent":2.8,"number":200,"code":"Wsh","name":"Karma Loop"},"echofon":{"percent":2.9,"number":209,"code":"U25","name":"Echofon"},"playboy":{"percent":2.9,"number":204,"code":"W4z","name":"Playboy"},"pizzahut":{"percent":2.9,"number":203,"code":"Mb0","name":"Pizza Hut"},"wendys":{"percent":3,"number":212,"code":"May","name":"Wendy's"},"kfc":{"percent":3,"number":215,"code":"Mav","name":"KFC"},"menshumor":{"percent":3,"number":215,"code":"Wa4","name":"Men's Humor"},"gq":{"percent":3,"number":212,"code":"W5v","name":"GQ"},"handm":{"percent":3,"number":215,"code":"Wkr","name":"H & M "},"ikea":{"percent":3.1,"number":218,"code":"B35","name":"Ikea"},"funnyordie":{"percent":3.1,"number":223,"code":"U5k","name":"Funny Or Die"},"costco":{"percent":3.2,"number":228,"code":"B19","name":"Costco"},"burgerking":{"percent":3.2,"number":225,"code":"Mb5","name":"Burger King"},"honda":{"percent":3.4,"number":241,"code":"B74","name":"Honda"},"tmz":{"percent":3.5,"number":252,"code":"Wa2","name":"TMZ"},"ihop":{"percent":3.5,"number":250,"code":"Mb6","name":"IHOP"},"applestore":{"percent":3.6,"number":255,"code":"B03","name":"Apple Store"},"playstation":{"percent":3.6,"number":256,"code":"U9e","name":"Playstation"},"louisvuitton":{"percent":3.6,"number":253,"code":"W40","name":"Louis Vuitton"},"bestbuy":{"percent":3.7,"number":261,"code":"B08","name":"Best Buy"},"ubersocial":{"percent":3.7,"number":263,"code":"u21","name":"Uber Social"},"vans":{"percent":3.7,"number":260,"code":"Wnf","name":"Vans"},"android":{"percent":3.8,"number":267,"code":"U10","name":"Android"},"gopro":{"percent":3.8,"number":270,"code":"Uag","name":"GoPro"},"eonline":{"percent":3.8,"number":274,"code":"Wg9","name":"E! Online"},"nationalgeographic":{"percent":3.9,"number":281,"code":"W4g","name":"National Geographic"},"marvel":{"percent":3.9,"number":276,"code":"U5q","name":"Marvel"},"samsung":{"percent":4,"number":284,"code":"U19","name":"Samsung"},"urbanoutfitters":{"percent":4,"number":287,"code":"W59","name":"Urban Outfitters"},"tumblr":{"percent":4.2,"number":298,"code":"U01","name":"Tumblr"},"chipotle":{"percent":4.3,"number":309,"code":"Max","name":"Chipotle"},"sephora":{"percent":4.6,"number":330,"code":"B50","name":"Sephora"},"9gag":{"percent":4.7,"number":334,"code":"Wa8","name":"9GAG"},"sneakernews":{"percent":4.8,"number":341,"code":"Wnh","name":"Sneaker News"},"subway":{"percent":4.8,"number":342,"code":"Mb2","name":"Subway"},"google":{"percent":5,"number":357,"code":"U46","name":"Google"},"footlocker":{"percent":5.1,"number":363,"code":"W30","name":"Foot Locker"},"omgfacts":{"percent":5.1,"number":366,"code":"W9u","name":"OMG Facts"},"uberfacts":{"percent":5.2,"number":371,"code":"W9w","name":"UberFacts"},"vine":{"percent":5.4,"number":387,"code":"U5j","name":"Vine"},"iphone":{"percent":5.5,"number":393,"code":"U12","name":"iPhone"},"forever21":{"percent":5.9,"number":417,"code":"W31","name":"Forever 21"},"cnn":{"percent":6.1,"number":432,"code":"Wfy","name":"CNN"},"adidas":{"percent":6.1,"number":432,"code":"Wn7","name":"Adidas"},"netflix":{"percent":6.5,"number":460,"code":"Ucp","name":"Netflix"},"facebook":{"percent":6.5,"number":461,"code":"U40","name":"Facebook"},"tacobell":{"percent":6.6,"number":472,"code":"Maw","name":"Taco Bell"},"victoriassecret":{"percent":6.6,"number":472,"code":"W60","name":"Victoria's Secret"},"target":{"percent":6.7,"number":475,"code":"B53","name":"Target"},"walmart":{"percent":7.8,"number":554,"code":"B59","name":"Walmart"},"espn":{"percent":8,"number":572,"code":"Wg1","name":"ESPN"},"mtv":{"percent":8.3,"number":591,"code":"Wg0","name":"MTV"},"disney":{"percent":8.4,"number":595,"code":"B23","name":"Disney"},"mcdonalds":{"percent":12.2,"number":867,"code":"Mau","name":"McDonald's"},"youtube":{"percent":14.1,"number":1006,"code":"U50","name":"Youtube"},"starbucks":{"percent":17.5,"number":1247,"code":"Mnh","name":"Starbucks"},"instagram":{"percent":20.9,"number":1489,"code":"U52","name":"Instagram"},"nike":{"percent":21.4,"number":1523,"code":"W46","name":"Nike"}},"likesinterests":{"equestrian":{"percent":0,"number":3,"code":"H1p","name":"Equestrian"},"gaylife":{"percent":0.1,"number":8,"code":"H81","name":"Gay life"},"flyingplanes":{"percent":0.1,"number":8,"code":"H40","name":"Flying planes"},"scubadiving":{"percent":0.1,"number":4,"code":"H1t","name":"Scuba diving"},"shopping":{"percent":0.1,"number":6,"code":"H23","name":"Shopping"},"environment":{"percent":0.1,"number":7,"code":"H32","name":"Environment"},"history":{"percent":0.1,"number":8,"code":"H41","name":"History"},"boating":{"percent":0.1,"number":8,"code":"H1r","name":"Boating"},"cricket":{"percent":0.2,"number":14,"code":"H1n","name":"Cricket"},"collectingthings":{"percent":0.2,"number":13,"code":"H34","name":"Collecting things"},"yoga":{"percent":0.2,"number":13,"code":"H3b","name":"Yoga"},"vegetarianism":{"percent":0.3,"number":23,"code":"H80","name":"Vegetarianism"},"writing":{"percent":0.4,"number":31,"code":"H79","name":"Writing"},"science":{"percent":0.4,"number":31,"code":"H11","name":"Science"},"motorsports":{"percent":0.4,"number":25,"code":"H1i","name":"Motor sports"},"bowling":{"percent":0.5,"number":38,"code":"H1x","name":"Bowling"},"charity":{"percent":0.5,"number":37,"code":"H08","name":"Charity"},"tea":{"percent":0.5,"number":36,"code":"H64","name":"Tea"},"cats":{"percent":0.6,"number":46,"code":"H2b","name":"Cats"},"homeimprovement":{"percent":0.6,"number":41,"code":"H35","name":"Home improvement"},"outdoorlife":{"percent":0.6,"number":46,"code":"H18","name":"Outdoor life"},"dogs":{"percent":0.6,"number":42,"code":"H2c","name":"Dogs"},"booksreading":{"percent":0.7,"number":49,"code":"H05","name":"Books/reading"},"petsanimals":{"percent":0.9,"number":62,"code":"H2a","name":"Pets/animals"},"smoking":{"percent":0.9,"number":65,"code":"H68","name":"Smoking"},"rugby":{"percent":1.1,"number":81,"code":"H1o","name":"Rugby"},"cycling":{"percent":1.1,"number":76,"code":"H1d","name":"Cycling"},"volleyball":{"percent":1.2,"number":88,"code":"H1v","name":"Volleyball"},"anime":{"percent":1.2,"number":88,"code":"H76","name":"Anime"},"fitness":{"percent":1.4,"number":102,"code":"H3a","name":"Fitness"},"artsandcrafts":{"percent":1.4,"number":100,"code":"H36","name":"Arts & crafts"},"business":{"percent":1.5,"number":107,"code":"H06","name":"Business"},"wine":{"percent":1.5,"number":105,"code":"H50","name":"Wine"},"travel":{"percent":1.6,"number":114,"code":"H25","name":"Travel"},"socialmedia":{"percent":1.7,"number":121,"code":"H4b","name":"Social Media"},"skiing":{"percent":1.7,"number":121,"code":"H1q","name":"Skiing"},"beer":{"percent":1.9,"number":136,"code":"H28","name":"Beer"},"skating":{"percent":1.9,"number":137,"code":"H1y","name":"Skating"},"healthissues":{"percent":2,"number":143,"code":"H42","name":"Health issues"},"golf":{"percent":2.2,"number":160,"code":"H1g","name":"Golf"},"cakecookies":{"percent":2.2,"number":158,"code":"H53","name":"Cake/cookies"},"politics":{"percent":2.3,"number":161,"code":"H21","name":"Politics"},"soccer":{"percent":2.4,"number":173,"code":"H1j","name":"Soccer"},"tennis":{"percent":2.5,"number":177,"code":"H1k","name":"Tennis"},"hockey":{"percent":2.8,"number":200,"code":"H1h","name":"Hockey"},"familylife":{"percent":2.9,"number":206,"code":"H12","name":"Family life"},"swimming":{"percent":3.5,"number":250,"code":"H1u","name":"Swimming"},"theater":{"percent":3.5,"number":251,"code":"H44","name":"Theater"},"cooking":{"percent":3.6,"number":257,"code":"H31","name":"Cooking"},"nightlifepartying":{"percent":3.8,"number":267,"code":"H67","name":"Nightlife/partying"},"surfing":{"percent":3.9,"number":277,"code":"H1s","name":"Surfing"},"coffee":{"percent":4.3,"number":304,"code":"H43","name":"Coffee"},"cars":{"percent":4.6,"number":325,"code":"H07","name":"Cars"},"extremesports":{"percent":4.6,"number":325,"code":"H1m","name":"Extreme sports"},"sciencefiction":{"percent":4.7,"number":337,"code":"H37","name":"Science fiction"},"datingromance":{"percent":5,"number":353,"code":"H16","name":"Dating/romance"},"kpop":{"percent":5.3,"number":378,"code":"H72","name":"K-Pop"},"gaming":{"percent":5.9,"number":417,"code":"H15","name":"Gaming"},"technology":{"percent":6.3,"number":445,"code":"H4a","name":"Technology"},"wininganddining":{"percent":6.9,"number":492,"code":"H14","name":"Wining & dining"},"news":{"percent":6.9,"number":490,"code":"H39","name":"News"},"baseball":{"percent":7.9,"number":564,"code":"H1b","name":"Baseball"},"wrestling":{"percent":8,"number":573,"code":"H1l","name":"Wrestling"},"boxingmma":{"percent":8.2,"number":587,"code":"H1e","name":"Boxing/MMA"},"photography":{"percent":8.8,"number":628,"code":"H20","name":"Photography"},"tvfilm":{"percent":8.9,"number":631,"code":"H26","name":"TV/film"},"artculture":{"percent":9.3,"number":660,"code":"H04","name":"Art/culture"},"fashion":{"percent":9.3,"number":665,"code":"H13","name":"Fashion"},"sports":{"percent":10.2,"number":725,"code":"H1a","name":"Sports"},"comedy":{"percent":11.4,"number":815,"code":"H09","name":"Comedy"},"football":{"percent":13.5,"number":959,"code":"H1f","name":"Football"},"basketball":{"percent":19.4,"number":1382,"code":"H1c","name":"Basketball"},"music":{"percent":23.7,"number":1687,"code":"H17","name":"Music"},"dancing":{"percent":24.7,"number":1760,"code":"H10","name":"Dancing"}},"occupations":{"churchleaders":{"percent":0.1,"number":1,"code":"P07","name":"Church leaders"},"itprofessionals":{"percent":0.1,"number":1,"code":"P54","name":"IT professionals"},"librarians":{"percent":0.1,"number":1,"code":"P19","name":"Librarians"},"politicsgovt":{"percent":0.1,"number":1,"code":"P23","name":"Politics/gov't."},"manufacturing":{"percent":0.1,"number":2,"code":"P50","name":"Manufacturing"},"scientists":{"percent":0.1,"number":1,"code":"P49","name":"Scientists"},"accountants":{"percent":0.1,"number":1,"code":"P33","name":"Accountants"},"pilots":{"percent":0.1,"number":1,"code":"P46","name":"Pilots"},"realtors":{"percent":0.2,"number":3,"code":"P24","name":"Realtors"},"publicservice":{"percent":0.2,"number":4,"code":"P38","name":"Public service"},"secretarialadmin":{"percent":0.2,"number":4,"code":"P52","name":"Secretarial/admin"},"homeservices":{"percent":0.2,"number":4,"code":"P40","name":"Home services"},"construction":{"percent":0.3,"number":6,"code":"P53","name":"Construction"},"investors":{"percent":0.3,"number":5,"code":"P44","name":"Investors"},"programmers":{"percent":0.3,"number":6,"code":"P2b","name":"Programmers"},"architects":{"percent":0.3,"number":6,"code":"P03","name":"Architects"},"financebanking":{"percent":0.3,"number":5,"code":"P34","name":"Finance/banking"},"lawyers":{"percent":0.3,"number":6,"code":"P18","name":"Lawyers"},"personaltrainers":{"percent":0.4,"number":7,"code":"P30","name":"Personal trainers"},"hospitality":{"percent":0.5,"number":9,"code":"P15","name":"Hospitality"},"doctors":{"percent":0.5,"number":8,"code":"P1b","name":"Doctors"},"comedians":{"percent":1,"number":18,"code":"P08","name":"Comedians"},"consultants":{"percent":1,"number":18,"code":"P35","name":"Consultants"},"teachers":{"percent":1,"number":17,"code":"P29","name":"Teachers"},"agentspromoters":{"percent":1.1,"number":19,"code":"P02","name":"Agents/promoters"},"chefs":{"percent":1.2,"number":20,"code":"P06","name":"Chefs"},"tvradiohosts":{"percent":1.3,"number":22,"code":"P16","name":"TV/radio hosts"},"designers":{"percent":1.3,"number":22,"code":"P10","name":"Designers"},"military":{"percent":1.3,"number":23,"code":"P45","name":"Military"},"models":{"percent":1.3,"number":23,"code":"P20","name":"Models"},"nurses":{"percent":1.4,"number":24,"code":"P1c","name":"Nurses"},"webdevelopers":{"percent":1.5,"number":25,"code":"P11","name":"Web developers"},"graphicdesign":{"percent":1.6,"number":27,"code":"P47","name":"Graphic design"},"actors":{"percent":1.7,"number":30,"code":"P01","name":"Actors"},"eventplanners":{"percent":1.7,"number":30,"code":"P41","name":"Event planners"},"stylists":{"percent":1.7,"number":29,"code":"P28","name":"Stylists"},"engineers":{"percent":2,"number":34,"code":"P2a","name":"Engineers"},"healthworkers":{"percent":2.2,"number":38,"code":"P1a","name":"Health workers"},"journalists":{"percent":2.4,"number":42,"code":"P17","name":"Journalists"},"authorswriters":{"percent":3,"number":52,"code":"P05","name":"Authors/writers"},"photographers":{"percent":3.3,"number":56,"code":"P22","name":"Photographers"},"dancers":{"percent":3.6,"number":62,"code":"P09","name":"Dancers"},"salesmarketing":{"percent":3.9,"number":67,"code":"P26","name":"Sales/marketing"},"mediaproduction":{"percent":5.5,"number":95,"code":"P31","name":"Media production"},"djs":{"percent":5.6,"number":96,"code":"P12","name":"DJs"},"entrepreneurs":{"percent":5.7,"number":98,"code":"P14","name":"Entrepreneurs"},"artists":{"percent":6.3,"number":108,"code":"P04","name":"Artists"},"seniormanagers":{"percent":7.2,"number":123,"code":"P32","name":"Senior managers"},"students":{"percent":9.4,"number":161,"code":"P55","name":"Students"},"musicians":{"percent":15,"number":257,"code":"P21","name":"Musicians"}},"locationbycity":{"kualalumpur":{"percent":0.2,"number":6,"code":"Th8","name":"Kuala Lumpur"},"adelaide":{"percent":0.2,"number":5,"code":"Tk9","name":"Adelaide"},"perth":{"percent":0.2,"number":6,"code":"Tk8","name":"Perth"},"palmbeachfl":{"percent":0.2,"number":6,"code":"TWG","name":"Palm Beach, FL"},"elkgroveca":{"percent":0.2,"number":6,"code":"TVT","name":"Elk Grove, CA"},"oxnardca":{"percent":0.2,"number":5,"code":"TVH","name":"Oxnard, CA"},"rentonwa":{"percent":0.2,"number":5,"code":"TU7","name":"Renton, WA"},"springfieldma":{"percent":0.2,"number":4,"code":"TTJ","name":"Springfield, MA"},"nashville":{"percent":0.2,"number":6,"code":"Tmh","name":"Nashville"},"rockvillemd":{"percent":0.2,"number":5,"code":"TT9","name":"Rockville, MD"},"jakarta":{"percent":0.2,"number":5,"code":"Tk3","name":"Jakarta"},"rochestermn":{"percent":0.2,"number":6,"code":"TSB","name":"Rochester, MN"},"napervilleil":{"percent":0.2,"number":4,"code":"TS3","name":"Naperville, IL"},"bangkok":{"percent":0.2,"number":5,"code":"Tjf","name":"Bangkok"},"santarosaca":{"percent":0.2,"number":6,"code":"TR4","name":"Santa Rosa, CA"},"evanstonil":{"percent":0.2,"number":6,"code":"TQY","name":"Evanston, IL"},"lawrenceks":{"percent":0.2,"number":4,"code":"TOQ","name":"Lawrence, KS"},"modestoca":{"percent":0.2,"number":5,"code":"TQW","name":"Modesto, CA"},"bakersfieldca":{"percent":0.2,"number":5,"code":"TPU","name":"Bakersfield, CA"},"jerseycitynj":{"percent":0.2,"number":5,"code":"TPT","name":"Jersey City, NJ"},"beverlyhillsca":{"percent":0.2,"number":5,"code":"TPL","name":"Beverly Hills, CA"},"jacksonville":{"percent":0.2,"number":6,"code":"Tnc","name":"Jacksonville"},"vacavilleca":{"percent":0.2,"number":6,"code":"T1U","name":"Vacaville, CA"},"sanleandroca":{"percent":0.2,"number":5,"code":"T1D","name":"San Leandro, CA"},"memphis":{"percent":0.2,"number":5,"code":"Tn0","name":"Memphis"},"saltlakecity":{"percent":0.2,"number":6,"code":"Tnz","name":"Salt Lake City"},"batonrouge":{"percent":0.2,"number":5,"code":"Tr2","name":"Baton Rouge"},"newarknj":{"percent":0.2,"number":6,"code":"Tqd","name":"Newark, NJ"},"dubai":{"percent":0.2,"number":4,"code":"Ta0","name":"Dubai"},"murfreesborotn":{"percent":0.2,"number":5,"code":"Tq8","name":"Murfreesboro, TN"},"reno":{"percent":0.2,"number":4,"code":"TOV","name":"Reno"},"lansingmi":{"percent":0.2,"number":5,"code":"Tp9","name":"Lansing, MI"},"alexandriava":{"percent":0.2,"number":4,"code":"Top","name":"Alexandria, VA"},"buffalo":{"percent":0.2,"number":6,"code":"Tnh","name":"Buffalo"},"cleveland":{"percent":0.2,"number":4,"code":"Tn8","name":"Cleveland"},"mississauga":{"percent":0.3,"number":7,"code":"TB8","name":"Mississauga"},"orlando":{"percent":0.3,"number":8,"code":"Tmp","name":"Orlando"},"yonkersny":{"percent":0.3,"number":7,"code":"Ttw","name":"Yonkers, NY"},"saintlouis":{"percent":0.3,"number":8,"code":"Tpa","name":"Saint Louis"},"virginiabeach":{"percent":0.3,"number":8,"code":"Tok","name":"Virginia Beach"},"milwaukee":{"percent":0.3,"number":7,"code":"Tmx","name":"Milwaukee"},"arlingtontx":{"percent":0.3,"number":8,"code":"TPQ","name":"Arlington, TX"},"sanantonio":{"percent":0.3,"number":8,"code":"Tn2","name":"San Antonio"},"anaheimca":{"percent":0.3,"number":7,"code":"TPM","name":"Anaheim, CA"},"phoenix":{"percent":0.4,"number":10,"code":"Tmq","name":"Phoenix"},"detroit":{"percent":0.4,"number":11,"code":"Tn5","name":"Detroit"},"tampa":{"percent":0.4,"number":11,"code":"Tn3","name":"Tampa"},"hongkong":{"percent":0.4,"number":9,"code":"Tk2","name":"Hong Kong"},"edmonton":{"percent":0.4,"number":11,"code":"Tkg","name":"Edmonton"},"covinaca":{"percent":0.4,"number":9,"code":"T1V","name":"Covina, CA"},"providenceri":{"percent":0.4,"number":9,"code":"Tob","name":"Providence, RI"},"edenprairiemn":{"percent":0.4,"number":9,"code":"TXA","name":"Eden Prairie, MN"},"austin":{"percent":0.4,"number":10,"code":"Tme","name":"Austin"},"miami":{"percent":0.4,"number":10,"code":"Tmr","name":"Miami"},"tucson":{"percent":0.5,"number":12,"code":"Tng","name":"Tucson"},"tacomawa":{"percent":0.5,"number":13,"code":"TOU","name":"Tacoma, WA"},"wichitaks":{"percent":0.5,"number":12,"code":"TOC","name":"Wichita, KS"},"desmoinesia":{"percent":0.5,"number":13,"code":"Toe","name":"Des Moines, IA"},"oklahomacity":{"percent":0.5,"number":12,"code":"T5f","name":"Oklahoma City"},"neworleans":{"percent":0.5,"number":13,"code":"Tqc","name":"New Orleans"},"kansascity":{"percent":0.5,"number":12,"code":"Tv0","name":"Kansas City"},"calgary":{"percent":0.5,"number":13,"code":"Tkb","name":"Calgary"},"winnipeg":{"percent":0.5,"number":14,"code":"Tki","name":"Winnipeg"},"singapore":{"percent":0.5,"number":12,"code":"Tk1","name":"Singapore"},"sanmateoca":{"percent":0.5,"number":12,"code":"TSZ","name":"San Mateo, CA"},"melbourne":{"percent":0.5,"number":14,"code":"Tk6","name":"Melbourne"},"lowellma":{"percent":0.5,"number":12,"code":"TTH","name":"Lowell, MA"},"haywardca":{"percent":0.5,"number":14,"code":"TX3","name":"Hayward, CA"},"charlotte":{"percent":0.5,"number":13,"code":"Tmm","name":"Charlotte"},"fremontca":{"percent":0.6,"number":15,"code":"TRL","name":"Fremont, CA"},"vancouver":{"percent":0.6,"number":16,"code":"Tkf","name":"Vancouver"},"washingtondc":{"percent":0.6,"number":15,"code":"Tmc","name":"Washington DC"},"atlanta":{"percent":0.7,"number":19,"code":"Tmb","name":"Atlanta"},"dallas":{"percent":0.7,"number":18,"code":"Tmk","name":"Dallas"},"portland":{"percent":0.7,"number":19,"code":"Tmu","name":"Portland"},"fresno":{"percent":0.7,"number":18,"code":"TO3","name":"Fresno"},"stocktonca":{"percent":0.8,"number":20,"code":"TQX","name":"Stockton, CA"},"manila":{"percent":0.9,"number":23,"code":"Tk4","name":"Manila"},"longbeachca":{"percent":0.9,"number":22,"code":"Tnk","name":"Long Beach, CA"},"oaklandca":{"percent":0.9,"number":23,"code":"Tne","name":"Oakland, CA"},"denver":{"percent":0.9,"number":23,"code":"Tmo","name":"Denver"},"montreal":{"percent":0.9,"number":24,"code":"Tkc","name":"Montreal"},"sydney":{"percent":0.9,"number":24,"code":"Tk7","name":"Sydney"},"london":{"percent":1,"number":26,"code":"Tkq","name":"London"},"boston":{"percent":1.1,"number":29,"code":"Tmd","name":"Boston"},"vallejoca":{"percent":1.1,"number":27,"code":"TXN","name":"Vallejo, CA"},"sacramento":{"percent":1.1,"number":28,"code":"Tn1","name":"Sacramento"},"philadelphia":{"percent":1.2,"number":30,"code":"Tml","name":"Philadelphia"},"minneapolis":{"percent":1.3,"number":34,"code":"Tmn","name":"Minneapolis"},"honolulu":{"percent":1.5,"number":39,"code":"To9","name":"Honolulu"},"toronto":{"percent":1.9,"number":48,"code":"Tke","name":"Toronto"},"seattle":{"percent":1.9,"number":49,"code":"Tmf","name":"Seattle"},"houston":{"percent":2.1,"number":53,"code":"Tmi","name":"Houston"},"lasvegas":{"percent":2.4,"number":61,"code":"Tms","name":"Las Vegas"},"sandiego":{"percent":2.7,"number":69,"code":"Tmj","name":"San Diego"},"sanjose":{"percent":2.9,"number":74,"code":"Tna","name":"San Jose"},"chicago":{"percent":3,"number":76,"code":"Tma","name":"Chicago"},"losangeles":{"percent":5,"number":127,"code":"Tm8","name":"Los Angeles"},"newyork":{"percent":5.3,"number":135,"code":"Tm9","name":"New York"},"sanfrancisco":{"percent":11.4,"number":289,"code":"Tmg","name":"San Francisco"}},"locationbyusstate":{"northdakota":{"percent":0,"number":1,"code":"SND","name":"North Dakota"},"montana":{"percent":0,"number":1,"code":"SMT","name":"Montana"},"wyoming":{"percent":0,"number":1,"code":"SWY","name":"Wyoming"},"delaware":{"percent":0.1,"number":3,"code":"SDE","name":"Delaware"},"idaho":{"percent":0.1,"number":2,"code":"SID","name":"Idaho"},"maine":{"percent":0.1,"number":3,"code":"SME","name":"Maine"},"newhampshire":{"percent":0.1,"number":2,"code":"SNH","name":"New Hampshire"},"nebraska":{"percent":0.1,"number":4,"code":"SNE","name":"Nebraska"},"southdakota":{"percent":0.1,"number":4,"code":"SSD","name":"South Dakota"},"alaska":{"percent":0.2,"number":6,"code":"SAK","name":"Alaska"},"kentucky":{"percent":0.2,"number":5,"code":"SKY","name":"Kentucky"},"mississippi":{"percent":0.3,"number":9,"code":"SMS","name":"Mississippi"},"utah":{"percent":0.3,"number":9,"code":"SUT","name":"Utah"},"rhodeisland":{"percent":0.3,"number":9,"code":"SRI","name":"Rhode Island"},"indiana":{"percent":0.3,"number":9,"code":"SIN","name":"Indiana"},"newmexico":{"percent":0.3,"number":9,"code":"SNM","name":"New Mexico"},"connecticut":{"percent":0.3,"number":10,"code":"SCT","name":"Connecticut"},"alabama":{"percent":0.4,"number":11,"code":"SAL","name":"Alabama"},"arkansas":{"percent":0.4,"number":11,"code":"SAR","name":"Arkansas"},"maryland":{"percent":0.5,"number":15,"code":"SMD","name":"Maryland"},"dc":{"percent":0.5,"number":15,"code":"SDC","name":"DC"},"wisconsin":{"percent":0.5,"number":14,"code":"SWI","name":"Wisconsin"},"southcarolina":{"percent":0.5,"number":13,"code":"SSC","name":"South Carolina"},"iowa":{"percent":0.6,"number":16,"code":"SIA","name":"Iowa"},"ohio":{"percent":0.7,"number":20,"code":"SOH","name":"Ohio"},"oklahoma":{"percent":0.7,"number":19,"code":"SOK","name":"Oklahoma"},"kansas":{"percent":0.7,"number":20,"code":"SKS","name":"Kansas"},"missouri":{"percent":0.8,"number":23,"code":"SMO","name":"Missouri"},"oregon":{"percent":0.8,"number":24,"code":"SOR","name":"Oregon"},"louisiana":{"percent":0.8,"number":23,"code":"SLA","name":"Louisiana"},"tennessee":{"percent":0.8,"number":22,"code":"STN","name":"Tennessee"},"michigan":{"percent":0.9,"number":26,"code":"SMI","name":"Michigan"},"georgia":{"percent":1.1,"number":33,"code":"SGA","name":"Georgia"},"colorado":{"percent":1.3,"number":38,"code":"SCO","name":"Colorado"},"virginia":{"percent":1.4,"number":39,"code":"SVA","name":"Virginia"},"northcarolina":{"percent":1.4,"number":40,"code":"SNC","name":"North Carolina"},"pennsylvania":{"percent":1.5,"number":42,"code":"SPA","name":"Pennsylvania"},"newjersey":{"percent":1.6,"number":47,"code":"SNJ","name":"New Jersey"},"arizona":{"percent":1.6,"number":46,"code":"SAZ","name":"Arizona"},"hawaii":{"percent":1.8,"number":53,"code":"SHI","name":"Hawaii"},"minnesota":{"percent":2.3,"number":66,"code":"SMN","name":"Minnesota"},"massachusetts":{"percent":2.3,"number":65,"code":"SMA","name":"Massachusetts"},"nevada":{"percent":2.4,"number":69,"code":"SNV","name":"Nevada"},"florida":{"percent":3.1,"number":90,"code":"SFL","name":"Florida"},"illinois":{"percent":3.6,"number":104,"code":"SIL","name":"Illinois"},"washington":{"percent":3.7,"number":106,"code":"SWA","name":"Washington"},"newyorkstate":{"percent":5.8,"number":168,"code":"SNY","name":"New York State"},"texas":{"percent":6.1,"number":175,"code":"STX","name":"Texas"},"california":{"percent":46.6,"number":1344,"code":"SCA","name":"California"}},"locationbycountry":{"sudan":{"percent":0,"number":1,"code":"CSD","name":"Sudan"},"laos":{"percent":0,"number":1,"code":"CLA","name":"Laos"},"israel":{"percent":0,"number":1,"code":"CIL","name":"Israel"},"iceland":{"percent":0,"number":1,"code":"CIS","name":"Iceland"},"switzerland":{"percent":0,"number":1,"code":"CCH","name":"Switzerland"},"barbados":{"percent":0,"number":1,"code":"CBB","name":"Barbados"},"paraguay":{"percent":0,"number":1,"code":"CPY","name":"Paraguay"},"honduras":{"percent":0,"number":1,"code":"CHN","name":"Honduras"},"guatemala":{"percent":0,"number":1,"code":"CGT","name":"Guatemala"},"pakistan":{"percent":0,"number":1,"code":"CPK","name":"Pakistan"},"greece":{"percent":0,"number":1,"code":"CGR","name":"Greece"},"turkey":{"percent":0,"number":1,"code":"CTR","name":"Turkey"},"portugal":{"percent":0,"number":1,"code":"CPT","name":"Portugal"},"nigeria":{"percent":0,"number":1,"code":"CNG","name":"Nigeria"},"russia":{"percent":0,"number":1,"code":"CRU","name":"Russia"},"ecuador":{"percent":0,"number":1,"code":"CEC","name":"Ecuador"},"latvia":{"percent":0,"number":1,"code":"CLV","name":"Latvia"},"lebanon":{"percent":0,"number":1,"code":"CLB","name":"Lebanon"},"kuwait":{"percent":0,"number":1,"code":"CKW","name":"Kuwait"},"taiwan":{"percent":0,"number":1,"code":"CTW","name":"Taiwan"},"kenya":{"percent":0,"number":1,"code":"CKE","name":"Kenya"},"cuba":{"percent":0,"number":1,"code":"CCU","name":"Cuba"},"jordan":{"percent":0,"number":1,"code":"CJO","name":"Jordan"},"austria":{"percent":0,"number":1,"code":"CAT","name":"Austria"},"china":{"percent":0,"number":1,"code":"CCN","name":"China"},"iran":{"percent":0,"number":1,"code":"CIR","name":"Iran"},"chile":{"percent":0,"number":1,"code":"CCL","name":"Chile"},"ireland":{"percent":0.1,"number":5,"code":"CIE","name":"Ireland"},"guam":{"percent":0.1,"number":2,"code":"CGU","name":"Guam"},"southafrica":{"percent":0.1,"number":3,"code":"CZA","name":"South Africa"},"venezuela":{"percent":0.1,"number":3,"code":"CVE","name":"Venezuela"},"puertorico":{"percent":0.1,"number":2,"code":"CPR","name":"Puerto Rico"},"spain":{"percent":0.1,"number":4,"code":"CES","name":"Spain"},"newzealand":{"percent":0.1,"number":4,"code":"CNZ","name":"New Zealand"},"netherlands":{"percent":0.1,"number":5,"code":"CNL","name":"Netherlands"},"uae":{"percent":0.1,"number":5,"code":"CAE","name":"UAE"},"colombia":{"percent":0.1,"number":2,"code":"CCO","name":"Colombia"},"sweden":{"percent":0.1,"number":3,"code":"CSE","name":"Sweden"},"brazil":{"percent":0.1,"number":5,"code":"CBR","name":"Brazil"},"jamaica":{"percent":0.1,"number":3,"code":"CJM","name":"Jamaica"},"belgium":{"percent":0.1,"number":4,"code":"CBE","name":"Belgium"},"india":{"percent":0.1,"number":4,"code":"CIN","name":"India"},"saudiarabia":{"percent":0.1,"number":2,"code":"CSA","name":"Saudi Arabia"},"cambodia":{"percent":0.1,"number":2,"code":"CKH","name":"Cambodia"},"argentina":{"percent":0.1,"number":2,"code":"CAR","name":"Argentina"},"indonesia":{"percent":0.2,"number":9,"code":"CID","name":"Indonesia"},"malaysia":{"percent":0.2,"number":9,"code":"CMY","name":"Malaysia"},"southkorea":{"percent":0.2,"number":6,"code":"CKR","name":"South Korea"},"italy":{"percent":0.2,"number":7,"code":"CIT","name":"Italy"},"thailand":{"percent":0.2,"number":9,"code":"CTH","name":"Thailand"},"france":{"percent":0.2,"number":7,"code":"CFR","name":"France"},"germany":{"percent":0.2,"number":9,"code":"CDE","name":"Germany"},"mexico":{"percent":0.3,"number":13,"code":"CMX","name":"Mexico"},"japan":{"percent":0.3,"number":13,"code":"CJP","name":"Japan"},"philippines":{"percent":1.1,"number":42,"code":"CPH","name":"Philippines"},"unitedkingdom":{"percent":1.8,"number":71,"code":"CGB","name":"United Kingdom"},"australia":{"percent":1.9,"number":74,"code":"CAU","name":"Australia"},"canada":{"percent":4.8,"number":189,"code":"CCA","name":"Canada"},"unitedstates":{"percent":86.1,"number":3374,"code":"CUS","name":"United States"}},"nativelanguage":{"lithuanian":{"percent":0,"number":1,"code":"LLT","name":"Lithuanian"},"albanian":{"percent":0,"number":2,"code":"LSQ","name":"Albanian"},"turkish":{"percent":0,"number":3,"code":"Ltr","name":"Turkish"},"catalan":{"percent":0,"number":3,"code":"LCA","name":"Catalan"},"thai":{"percent":0,"number":1,"code":"LTH","name":"Thai"},"polish":{"percent":0,"number":3,"code":"LPL","name":"Polish"},"finnish":{"percent":0,"number":2,"code":"LFI","name":"Finnish"},"persian":{"percent":0,"number":1,"code":"LFA","name":"Persian"},"greek":{"percent":0,"number":1,"code":"LEL","name":"Greek"},"chinese":{"percent":0.1,"number":6,"code":"LZH","name":"Chinese"},"arabic":{"percent":0.1,"number":5,"code":"LAR","name":"Arabic"},"indonesian":{"percent":0.1,"number":4,"code":"Lid","name":"Indonesian"},"french":{"percent":0.1,"number":4,"code":"Lfr","name":"French"},"dutch":{"percent":0.1,"number":4,"code":"Lnl","name":"Dutch"},"japanese":{"percent":0.1,"number":5,"code":"Lja","name":"Japanese"},"portuguese":{"percent":0.2,"number":11,"code":"Lpt","name":"Portuguese"},"german":{"percent":0.2,"number":10,"code":"Lde","name":"German"},"tagalog":{"percent":0.3,"number":19,"code":"LTL","name":"Tagalog"},"italian":{"percent":0.3,"number":16,"code":"Lit","name":"Italian"},"spanish":{"percent":0.8,"number":50,"code":"Les","name":"Spanish"},"english":{"percent":97.6,"number":6014,"code":"Len","name":"English"}},"raceusonly":{"asian":{"percent":13.2,"number":152,"code":"E04","name":"Asian"},"africanamerican":{"percent":20,"number":231,"code":"E02","name":"African American"},"hispanic":{"percent":26.4,"number":304,"code":"E03","name":"Hispanic"},"whitecaucasian":{"percent":40.4,"number":466,"code":"E01","name":"White/caucasian"}},"personalincome":{"75000to99999":{"percent":0.3,"number":7,"code":"O07","name":"$75,000 - $99,999"},"50000to74999":{"percent":2.4,"number":55,"code":"O06","name":"$50,000 - $74,999"},"40000to49999":{"percent":5.3,"number":120,"code":"O05","name":"$40,000 - $49,999"},"30000to39999":{"percent":12,"number":269,"code":"O04","name":"$30,000 - $39,999"},"20000to29999":{"percent":20.8,"number":467,"code":"O03","name":"$20,000 - $29,999"},"under10000":{"percent":21.5,"number":482,"code":"O01","name":"Under $10,000"},"10000to19999":{"percent":37.7,"number":847,"code":"O02","name":"$10,000 - $19,999"}},"agenielsen":{"age55to64":{"percent":0,"number":1,"code":"G18","name":"Age 55 to 64"},"age65andover":{"percent":0.1,"number":2,"code":"G19","name":"Age 65 and over"},"age45to54":{"percent":0.3,"number":7,"code":"G17","name":"Age 45 to 54"},"age35to44":{"percent":1.9,"number":46,"code":"G16","name":"Age 35 to 44"},"age17andunder":{"percent":3.9,"number":92,"code":"G11","name":"Age 17 and under"},"age30to34":{"percent":4.6,"number":111,"code":"G15","name":"Age 30 to 34"},"age25to29":{"percent":18.2,"number":435,"code":"G14","name":"Age 25 to 29"},"age18to20":{"percent":34.2,"number":818,"code":"G12","name":"Age 18 to 20"},"age21to24":{"percent":36.7,"number":877,"code":"G13","name":"Age 21 to 24"}},"agecensus":{"age60andover":{"percent":0.1,"number":2,"code":"G09","name":"Age 60 and over"},"age50to59":{"percent":0.2,"number":4,"code":"G08","name":"Age 50 to 59"},"age40to49":{"percent":0.8,"number":19,"code":"G07","name":"Age 40 to 49"},"age16andunder":{"percent":1,"number":23,"code":"G01","name":"Age 16 and under"},"age35to39":{"percent":1.3,"number":31,"code":"G06","name":"Age 35 to 39"},"age30to34":{"percent":4.6,"number":111,"code":"G05","name":"Age 30 to 34"},"age25to29":{"percent":18.2,"number":435,"code":"G04","name":"Age 25 to 29"},"age17to19":{"percent":25.2,"number":601,"code":"G02","name":"Age 17 to 19"},"age20to24":{"percent":48.7,"number":1163,"code":"G03","name":"Age 20 to 24"}},"familystatus":{"parents":{"percent":13.4,"number":953,"code":"D04","name":"Parents"},"married":{"percent":26.7,"number":283,"code":"D03","name":"Married"},"single":{"percent":73.3,"number":775,"code":"D09","name":"Single"}},"gender":{"female":{"percent":45.1,"number":2677,"code":"D02","name":"Female"},"male":{"percent":54.9,"number":3253,"code":"D01","name":"Male"}}},"status":"complete","errorMessage":"","errorCode":null,"error_details":"","network":"instagram","handle":"meeshthesinger","__v":0,"deleted":false}}
