{"result":{"_id":"56f2f3bb32ecb61a16ce5a75","data":{"locationbycity":{"edinburgh":{"name":"Edinburgh","number":17,"percent":0.3},"plymouth":{"number":17,"percent":0.3,"name":"Plymouth"},"manchesteruk":{"percent":1.1,"name":"Manchester, UK","number":65},"pittsburgh":{"name":"Pittsburgh","number":36,"percent":0.6},"melbourne":{"name":"Melbourne","number":23,"percent":0.4},"guarulhos":{"name":"Guarulhos","number":21,"percent":0.3},"copenhagen":{"name":"Copenhagen","number":17,"percent":0.3},"moscow":{"name":"Moscow","number":17,"percent":0.3},"sanfrancisco":{"name":"San Francisco","number":17,"percent":0.3},"cincinnati":{"name":"Cincinnati","number":15,"percent":0.2},"losangeles":{"name":"Los Angeles","number":63,"percent":1},"atlanta":{"number":49,"percent":0.8,"name":"Atlanta"},"cleveland":{"percent":0.5,"name":"Cleveland","number":30},"glasgow":{"name":"Glasgow","number":25,"percent":0.4},"charlotte":{"name":"Charlotte","number":18,"percent":0.3},"tampa":{"name":"Tampa","number":15,"percent":0.2},"leicester":{"number":19,"percent":0.3,"name":"Leicester"},"bogota":{"name":"Bogota","number":18,"percent":0.3},"ottawa":{"percent":0.3,"name":"Ottawa","number":17},"cardiff":{"name":"Cardiff","number":35,"percent":0.6},"stockholm":{"name":"Stockholm","number":29,"percent":0.5},"liverpool":{"name":"Liverpool","number":29,"percent":0.5},"vancouver":{"name":"Vancouver","number":26,"percent":0.4},"sanantonio":{"name":"San Antonio","number":19,"percent":0.3},"nashville":{"name":"Nashville","number":23,"percent":0.4},"fortaleza":{"name":"Fortaleza","number":18,"percent":0.3},"kansascity":{"name":"Kansas City","number":18,"percent":0.3},"cairo":{"number":32,"percent":0.5,"name":"Cairo"},"saintlouis":{"percent":0.5,"name":"Saint Louis","number":30},"sydney":{"name":"Sydney","number":27,"percent":0.4},"calgary":{"number":27,"percent":0.4,"name":"Calgary"},"saltlakecity":{"name":"Salt Lake City","number":23,"percent":0.4},"sevilla":{"name":"Sevilla","number":16,"percent":0.3},"columbiasc":{"percent":0.2,"name":"Columbia, SC","number":15},"paris":{"name":"Paris","number":31,"percent":0.5},"montreal":{"number":25,"percent":0.4,"name":"Montreal"},"columbus":{"name":"Columbus","number":20,"percent":0.3},"washingtondc":{"name":"Washington DC","number":17,"percent":0.3},"derby":{"name":"Derby","number":15,"percent":0.2},"dublin":{"name":"Dublin","number":30,"percent":0.5},"curitiba":{"percent":0.4,"name":"Curitiba","number":25},"detroit":{"name":"Detroit","number":21,"percent":0.3},"akronoh":{"name":"Akron, OH","number":16,"percent":0.3},"riodejaneiro":{"number":87,"percent":1.4,"name":"Rio de Janeiro"},"istanbul":{"name":"Istanbul","number":47,"percent":0.8},"denver":{"name":"Denver","number":30,"percent":0.5},"johannesburg":{"name":"Johannesburg","number":21,"percent":0.3},"brighton":{"name":"Brighton","number":17,"percent":0.3},"oxforduk":{"name":"Oxford, UK","number":15,"percent":0.2},"london":{"percent":3.8,"name":"London","number":231},"bristol":{"name":"Bristol","number":26,"percent":0.4},"leeds":{"name":"Leeds","number":24,"percent":0.4},"providenceri":{"name":"Providence, RI","number":17,"percent":0.3},"malaga":{"name":"Malaga","number":16,"percent":0.3},"buenosaires":{"name":"Buenos Aires","number":81,"percent":1.3},"boston":{"name":"Boston","number":26,"percent":0.4},"houston":{"name":"Houston","number":18,"percent":0.3},"buffalo":{"name":"Buffalo","number":16,"percent":0.3},"edmonton":{"number":14,"percent":0.2,"name":"Edmonton"},"lansingmi":{"name":"Lansing, MI","number":17,"percent":0.3},"newyork":{"name":"New York","number":105,"percent":1.7},"santiago":{"name":"Santiago","number":64,"percent":1},"barcelona":{"percent":0.6,"name":"Barcelona","number":37},"birminghamuk":{"name":"Birmingham, UK","number":25,"percent":0.4},"baltimore":{"name":"Baltimore","number":23,"percent":0.4},"jacksonville":{"name":"Jacksonville","number":18,"percent":0.3},"recife":{"name":"Recife","number":17,"percent":0.3},"milano":{"name":"Milano","number":16,"percent":0.3},"saopaulo":{"name":"Sao Paulo","number":245,"percent":4},"portland":{"name":"Portland","number":27,"percent":0.4},"indianapolis":{"name":"Indianapolis","number":26,"percent":0.4},"bournemouth":{"name":"Bournemouth","number":25,"percent":0.4},"caracas":{"name":"Caracas","number":20,"percent":0.3},"newcastle":{"name":"Newcastle","number":36,"percent":0.6},"dallas":{"name":"Dallas","number":27,"percent":0.4},"miami":{"name":"Miami","number":27,"percent":0.4},"norwich":{"name":"Norwich","number":19,"percent":0.3},"belfast":{"number":22,"percent":0.4,"name":"Belfast"},"brisbane":{"percent":0.3,"name":"Brisbane","number":20},"guatemalacity":{"name":"Guatemala City","number":16,"percent":0.3},"sandiego":{"name":"San Diego","number":37,"percent":0.6},"roma":{"name":"Roma","number":30,"percent":0.5},"minneapolis":{"number":29,"percent":0.5,"name":"Minneapolis"},"valencia":{"name":"Valencia","number":25,"percent":0.4},"austin":{"percent":0.4,"name":"Austin","number":23},"lima":{"name":"Lima","number":15,"percent":0.2},"toronto":{"name":"Toronto","number":59,"percent":1},"belohorizonte":{"name":"Belo Horizonte","number":22,"percent":0.4},"capetown":{"name":"Cape Town","number":18,"percent":0.3},"southampton":{"name":"Southampton","number":18,"percent":0.3},"lasvegas":{"name":"Las Vegas","number":16,"percent":0.3},"madrid":{"name":"Madrid","number":81,"percent":1.3},"portoalegre":{"number":43,"percent":0.7,"name":"Porto Alegre"},"mexicocity":{"percent":0.7,"name":"Mexico City","number":41},"nottingham":{"name":"Nottingham","number":24,"percent":0.4},"philadelphia":{"name":"Philadelphia","number":49,"percent":0.8},"chicago":{"name":"Chicago","number":48,"percent":0.8},"orlando":{"name":"Orlando","number":24,"percent":0.4},"milwaukee":{"name":"Milwaukee","number":16,"percent":0.3},"northampton":{"number":15,"percent":0.2,"name":"Northampton"}},"accountsfollowed":{"10to100accounts":{"name":"10-100 accounts","number":509,"percent":2},"under10accounts":{"name":"< 10 accounts","number":4,"percent":0},"101to1000accounts":{"name":"101-1,000 accounts","number":21035,"percent":82.7},"over1000accounts":{"number":3868,"percent":15.2,"name":"> 1,000 accounts"}},"likesinterests":{"familylife":{"name":"Family life","number":215,"percent":0.8},"motorsports":{"name":"Motor sports","number":50,"percent":0.2},"fitness":{"name":"Fitness","number":310,"percent":1.2},"boxingmma":{"name":"Boxing/MMA","number":64,"percent":0.3},"collectingthings":{"name":"Collecting things","number":35,"percent":0.1},"golf":{"name":"Golf","number":33,"percent":0.1},"tvfilm":{"name":"TV/film","number":638,"percent":2.5},"politics":{"name":"Politics","number":464,"percent":1.8},"surfing":{"number":14,"percent":0.1,"name":"Surfing"},"fashion":{"name":"Fashion","number":1202,"percent":4.7},"boating":{"percent":0.1,"name":"Boating","number":17},"sciencefiction":{"name":"Science fiction","number":130,"percent":0.5},"baseball":{"name":"Baseball","number":40,"percent":0.2},"flyingplanes":{"name":"Flying planes","number":7,"percent":0},"scubadiving":{"number":5,"percent":0,"name":"Scuba diving"},"healthissues":{"name":"Health issues","number":215,"percent":0.8},"charity":{"name":"Charity","number":136,"percent":0.5},"extremesports":{"name":"Extreme sports","number":142,"percent":0.6},"dogs":{"percent":0.5,"name":"Dogs","number":130},"football":{"name":"Football","number":121,"percent":0.5},"cycling":{"name":"Cycling","number":72,"percent":0.3},"kpop":{"name":"K-Pop","number":4,"percent":0},"music":{"name":"Music","number":2293,"percent":9},"cats":{"name":"Cats","number":252,"percent":1},"cricket":{"number":9,"percent":0,"name":"Cricket"},"travel":{"name":"Travel","number":359,"percent":1.4},"tennis":{"percent":0.3,"name":"Tennis","number":73},"history":{"name":"History","number":56,"percent":0.2},"skiing":{"name":"Skiing","number":38,"percent":0.1},"cakecookies":{"name":"Cake/cookies","number":32,"percent":0.1},"smoking":{"name":"Smoking","number":17,"percent":0.1},"booksreading":{"name":"Books/reading","number":598,"percent":2.3},"technology":{"number":418,"percent":1.6,"name":"Technology"},"swimming":{"percent":0.1,"name":"Swimming","number":13},"artsandcrafts":{"name":"Arts & crafts","number":202,"percent":0.8},"yoga":{"name":"Yoga","number":165,"percent":0.6},"shopping":{"number":15,"percent":0.1,"name":"Shopping"},"artculture":{"percent":6.5,"name":"Art/culture","number":1656},"sports":{"name":"Sports","number":309,"percent":1.2},"comedy":{"number":904,"percent":3.6,"name":"Comedy"},"dancing":{"name":"Dancing","number":294,"percent":1.2},"theater":{"percent":0.3,"name":"Theater","number":67},"vegetarianism":{"name":"Vegetarianism","number":40,"percent":0.2},"hockey":{"name":"Hockey","number":36,"percent":0.1},"bowling":{"name":"Bowling","number":1,"percent":0},"writing":{"name":"Writing","number":117,"percent":0.5},"business":{"name":"Business","number":84,"percent":0.3},"beer":{"number":44,"percent":0.2,"name":"Beer"},"environment":{"name":"Environment","number":144,"percent":0.6},"anime":{"name":"Anime","number":64,"percent":0.3},"science":{"percent":0.3,"name":"Science","number":89},"skating":{"name":"Skating","number":11,"percent":0},"photography":{"number":629,"percent":2.5,"name":"Photography"},"socialmedia":{"name":"Social Media","number":187,"percent":0.7},"tea":{"name":"Tea","number":156,"percent":0.6},"nightlifepartying":{"name":"Nightlife/partying","number":140,"percent":0.6},"datingromance":{"percent":1.7,"name":"Dating/romance","number":428},"soccer":{"name":"Soccer","number":407,"percent":1.6},"basketball":{"name":"Basketball","number":311,"percent":1.2},"coffee":{"name":"Coffee","number":270,"percent":1.1},"wrestling":{"name":"Wrestling","number":71,"percent":0.3},"homeimprovement":{"name":"Home improvement","number":45,"percent":0.2},"news":{"name":"News","number":745,"percent":2.9},"outdoorlife":{"name":"Outdoor life","number":626,"percent":2.5},"gaylife":{"name":"Gay life","number":19,"percent":0.1},"rugby":{"number":10,"percent":0,"name":"Rugby"},"volleyball":{"percent":0.1,"name":"Volleyball","number":15},"petsanimals":{"name":"Pets/animals","number":623,"percent":2.4},"wininganddining":{"number":554,"percent":2.2,"name":"Wining & dining"},"cars":{"percent":0.2,"name":"Cars","number":42},"equestrian":{"name":"Equestrian","number":32,"percent":0.1},"wine":{"name":"Wine","number":28,"percent":0.1},"gaming":{"name":"Gaming","number":258,"percent":1},"cooking":{"name":"Cooking","number":221,"percent":0.9}},"hashtags":{"baby":{"name":"#baby","number":2424,"percent":9.5},"coffee":{"name":"#coffee","number":2140,"percent":8.4},"shopping":{"name":"#shopping","number":1432,"percent":5.6},"ocean":{"name":"#ocean","number":1397,"percent":5.5},"beautiful":{"number":5512,"percent":21.7,"name":"#beautiful"},"sky":{"name":"#sky","number":3028,"percent":11.9},"pretty":{"name":"#pretty","number":2854,"percent":11.2},"beauty":{"percent":10.2,"name":"#beauty","number":2590},"vegan":{"name":"#vegan","number":1324,"percent":5.2},"dog":{"name":"#dog","number":2884,"percent":11.3},"amazing":{"name":"#amazing","number":2353,"percent":9.2},"happiness":{"name":"#happiness","number":2089,"percent":8.2},"tea":{"number":1832,"percent":7.2,"name":"#tea"},"home":{"percent":9.2,"name":"#home","number":2353},"fashion":{"name":"#fashion","number":2174,"percent":8.5},"tree":{"name":"#tree","number":2127,"percent":8.4},"bored":{"name":"#bored","number":1948,"percent":7.7},"love":{"name":"#love","number":9595,"percent":37.7},"selfie":{"name":"#selfie","number":5627,"percent":22.1},"art":{"name":"#art","number":5225,"percent":20.5},"night":{"number":2691,"percent":10.6,"name":"#night"},"loveit":{"name":"#loveit","number":1560,"percent":6.1},"delicious":{"percent":5.1,"name":"#delicious","number":1298},"glasses":{"name":"#glasses","number":1321,"percent":5.2},"perfect":{"name":"#perfect","number":1535,"percent":6},"adorable":{"name":"#adorable","number":1404,"percent":5.5},"yoga":{"name":"#yoga","number":1343,"percent":5.3},"festival":{"name":"#festival","number":1322,"percent":5.2},"dinner":{"name":"#dinner","number":1359,"percent":5.3},"music":{"name":"#music","number":4056,"percent":15.9},"chocolate":{"number":1887,"percent":7.4,"name":"#chocolate"},"dreads":{"percent":7,"name":"#dreads","number":1773},"boyfriend":{"name":"#boyfriend","number":1623,"percent":6.4},"beer":{"name":"#beer","number":1315,"percent":5.2},"hippie":{"name":"#hippie","number":2277,"percent":8.9},"vintage":{"name":"#vintage","number":2102,"percent":8.3},"ootd":{"name":"#ootd","number":1932,"percent":7.6},"book":{"name":"#book","number":1381,"percent":5.4},"life":{"number":3529,"percent":13.9,"name":"#life"},"cat":{"name":"#cat","number":3468,"percent":13.6},"drawing":{"percent":9.7,"name":"#drawing","number":2460},"flower":{"name":"#flower","number":2351,"percent":9.2},"blonde":{"name":"#blonde","number":1562,"percent":6.1},"cool":{"name":"#cool","number":1539,"percent":6},"dress":{"name":"#dress","number":1531,"percent":6},"garden":{"number":1445,"percent":5.7,"name":"#garden"},"sunset":{"name":"#sunset","number":3800,"percent":14.9},"snow":{"name":"#snow","number":2330,"percent":9.2},"moon":{"name":"#moon","number":1936,"percent":7.6},"shoes":{"name":"#shoes","number":1595,"percent":6.3},"sunrise":{"name":"#sunrise","number":1329,"percent":5.2},"swag":{"name":"#swag","number":1282,"percent":5},"awesome":{"percent":5.7,"name":"#awesome","number":1462},"nails":{"name":"#nails","number":1408,"percent":5.5},"happy":{"name":"#happy","number":5768,"percent":22.7},"flowers":{"name":"#flowers","number":4007,"percent":15.7},"travel":{"name":"#travel","number":1733,"percent":6.8},"tired":{"name":"#tired","number":1515,"percent":6},"kitty":{"name":"#kitty","number":1643,"percent":6.5},"pizza":{"name":"#pizza","number":1382,"percent":5.4},"nature":{"name":"#nature","number":5341,"percent":21},"photography":{"name":"#photography","number":1830,"percent":7.2},"bestfriends":{"name":"#bestfriends","number":1817,"percent":7.1},"style":{"number":1648,"percent":6.5,"name":"#style"},"family":{"name":"#family","number":3898,"percent":15.3},"food":{"name":"#food","number":3153,"percent":12.4},"puppy":{"name":"#puppy","number":1669,"percent":6.6},"rainbow":{"name":"#rainbow","number":1644,"percent":6.5},"clouds":{"name":"#clouds","number":2018,"percent":7.9},"foodporn":{"percent":7,"name":"#FoodPorn","number":1779},"yum":{"name":"#yum","number":1775,"percent":7},"breakfast":{"number":1772,"percent":7,"name":"#breakfast"},"cute":{"name":"#cute","number":5005,"percent":19.7},"friends":{"name":"#friends","number":4824,"percent":19},"tattoo":{"name":"#tattoo","number":2880,"percent":11.3},"work":{"name":"#work","number":2028,"percent":8},"relax":{"percent":6.9,"name":"#relax","number":1744},"goodvibes":{"name":"#goodvibes","number":1689,"percent":6.6},"sister":{"name":"#sister","number":1661,"percent":6.5},"natural":{"number":1580,"percent":6.2,"name":"#natural"},"painting":{"percent":6.3,"name":"#painting","number":1612},"sun":{"name":"#sun","number":4449,"percent":17.5},"hair":{"name":"#hair","number":3697,"percent":14.5},"sea":{"number":1781,"percent":7,"name":"#sea"},"school":{"name":"#school","number":1723,"percent":6.8},"cake":{"percent":5.3,"name":"#cake","number":1337},"forest":{"name":"#forest","number":1291,"percent":5.1},"peace":{"number":3433,"percent":13.5,"name":"#peace"},"girl":{"name":"#girl","number":3178,"percent":12.5},"funny":{"name":"#funny","number":2150,"percent":8.4},"healthy":{"name":"#healthy","number":1882,"percent":7.4},"makeup":{"name":"#makeup","number":2661,"percent":10.5},"yummy":{"name":"#yummy","number":1809,"percent":7.1},"holiday":{"percent":5.6,"name":"#holiday","number":1424},"inspiration":{"name":"#inspiration","number":1355,"percent":5.3},"handmade":{"number":1338,"percent":5.3,"name":"#handmade"},"beach":{"percent":13.7,"name":"#beach","number":3492},"party":{"name":"#party","number":2823,"percent":11.1},"bestfriend":{"name":"#bestfriend","number":2297,"percent":9},"sunshine":{"name":"#sunshine","number":2262,"percent":8.9}},"influences":{"jaredleto":{"name":"Jared Leto","number":2089,"percent":8.2},"krisjenner":{"name":"Kris Jenner","number":975,"percent":3.8},"jamieoliver":{"name":"Jamie Oliver","number":703,"percent":2.8},"justintimberlake":{"name":"Justin Timberlake","number":2354,"percent":9.2},"starbuckscoffee":{"name":"Starbucks Coffee","number":1306,"percent":5.1},"avrillavigne":{"name":"Avril Lavigne","number":1289,"percent":5.1},"kevinhart":{"name":"Kevin Hart","number":1178,"percent":4.6},"danieltosh":{"number":867,"percent":3.4,"name":"Daniel Tosh"},"petewentz":{"name":"Pete Wentz","number":821,"percent":3.2},"nationalgeographic":{"name":"National Geographic","number":3612,"percent":14.2},"hayleywilliams":{"percent":7.3,"name":"Hayley Williams","number":1858},"britneyspears":{"name":"Britney Spears","number":1809,"percent":7.1},"drake":{"name":"Drake","number":1388,"percent":5.5},"kellyosbourne":{"name":"Kelly Osbourne","number":1333,"percent":5.2},"chrisbrown":{"name":"Chris Brown","number":1243,"percent":4.9},"joejonas":{"name":"Joe Jonas","number":964,"percent":3.8},"fearnecotton":{"number":913,"percent":3.6,"name":"Fearne Cotton"},"kimkardashian":{"percent":14.5,"name":"Kim Kardashian","number":3680},"debbyryan":{"name":"Debby Ryan","number":842,"percent":3.3},"leightonmeester":{"number":767,"percent":3,"name":"Leighton Meester"},"victoriajustice":{"name":"Victoria Justice","number":855,"percent":3.4},"hilaryduff":{"percent":6,"name":"Hilary Duff","number":1535},"shakira":{"name":"Shakira","number":1235,"percent":4.9},"adele":{"name":"Adele","number":1072,"percent":4.2},"tomfelton":{"number":1028,"percent":4,"name":"Tom Felton"},"aliciakeys":{"name":"Alicia Keys","number":839,"percent":3.3},"calvinharris":{"percent":3.3,"name":"Calvin Harris","number":834},"robkardashian":{"name":"Rob Kardashian","number":723,"percent":2.8},"justinbieber":{"number":3036,"percent":11.9,"name":"Justin Bieber"},"lucyhale":{"percent":8.5,"name":"Lucy Hale","number":2165},"ninadobrev":{"name":"Nina Dobrev","number":1257,"percent":4.9},"keha":{"number":1162,"percent":4.6,"name":"Ke$ha"},"macmiller":{"percent":3.9,"name":"Mac Miller","number":981},"davidguetta":{"name":"David Guetta","number":847,"percent":3.3},"neymarjr":{"number":842,"percent":3.3,"name":"Neymar Jr."},"rihanna":{"name":"Rihanna","number":4133,"percent":16.2},"nickiminaj":{"name":"Nicki Minaj","number":3161,"percent":12.4},"khlokardashian":{"name":"Khloé Kardashian","number":3132,"percent":12.3},"jessiej":{"percent":5.5,"name":"Jessie J","number":1397},"tyrabanks":{"name":"Tyra Banks","number":1157,"percent":4.5},"nicolerichie":{"name":"Nicole Richie","number":1115,"percent":4.4},"jimmyfallon":{"name":"Jimmy Fallon","number":963,"percent":3.8},"victoriabeckham":{"name":"Victoria Beckham","number":910,"percent":3.6},"ladygaga":{"name":"Lady Gaga","number":4082,"percent":16},"snoopdogg":{"number":1592,"percent":6.3,"name":"Snoop Dogg"},"barackobama":{"name":"Barack Obama","number":1186,"percent":4.7},"nasa":{"percent":4.6,"name":"NASA","number":1161},"jwowwfarley":{"name":"JWoww Farley","number":974,"percent":3.8},"oprahwinfrey":{"name":"Oprah Winfrey","number":925,"percent":3.6},"codysimpson":{"number":822,"percent":3.2,"name":"Cody Simpson"},"kourtneykardashian":{"name":"Kourtney Kardashian","number":2552,"percent":10},"parishilton":{"name":"Paris Hilton","number":1228,"percent":4.8},"johngreen":{"name":"John Green","number":1200,"percent":4.7},"mtv":{"percent":4.6,"name":"MTV","number":1168},"jadensmith":{"name":"Jaden Smith","number":956,"percent":3.8},"robdyrdek":{"name":"Rob Dyrdek","number":703,"percent":2.8},"demilovato":{"number":3594,"percent":14.1,"name":"Demi Lovato"},"pnk":{"name":"P!nk","number":1318,"percent":5.2},"leamichele":{"percent":3.1,"name":"Lea Michele","number":792},"mileycyrus":{"name":"Miley Cyrus","number":6061,"percent":23.8},"lindsaylohan":{"name":"Lindsay Lohan","number":2034,"percent":8},"emmawatson":{"name":"Emma Watson","number":2131,"percent":8.4},"scottdisick":{"name":"Scott Disick","number":1496,"percent":5.9},"mirandacosgrove":{"name":"Miranda Cosgrove","number":792,"percent":3.1},"katyperry":{"name":"Katy Perry","number":4505,"percent":17.7},"selenagomez":{"name":"Selena Gomez","number":3825,"percent":15},"urbanoutfitters":{"name":"Urban Outfitters","number":2583,"percent":10.1},"snookipolizzi":{"name":"Snooki Polizzi","number":1786,"percent":7},"ashleytisdale":{"number":1576,"percent":6.2,"name":"Ashley Tisdale"},"iansomerhalder":{"name":"Ian Somerhalder","number":1477,"percent":5.8},"ditavonteese":{"percent":5,"name":"Dita Von Teese","number":1276},"ashtonkutcher":{"name":"Ashton Kutcher","number":1190,"percent":4.7},"kendalljenner":{"name":"Kendall Jenner","number":4413,"percent":17.3},"charliesheen":{"name":"Charlie Sheen","number":779,"percent":3.1},"coldplay":{"number":1069,"percent":4.2,"name":"Coldplay"},"wizkhalifa":{"percent":8.9,"name":"Wiz Khalifa","number":2257},"jenniferlopez":{"name":"Jennifer Lopez","number":1770,"percent":7},"neilpatrickharris":{"name":"Neil Patrick Harris","number":1141,"percent":4.5},"lilwayne":{"number":1022,"percent":4,"name":"Lil Wayne"},"dalailama":{"percent":2.9,"name":"Dalai Lama","number":732},"katvond":{"name":"Kat Von D","number":2815,"percent":11.1},"arianagrande":{"name":"Ariana Grande","number":3452,"percent":13.6},"ellendegeneres":{"name":"Ellen DeGeneres","number":2924,"percent":11.5},"channingtatum":{"name":"Channing Tatum","number":1283,"percent":5},"youtube":{"number":1229,"percent":4.8,"name":"YouTube"},"nickjonas":{"percent":4.8,"name":"Nick Jonas","number":1226},"shanedawson":{"name":"Shane Dawson","number":941,"percent":3.7},"rollingstone":{"number":779,"percent":3.1,"name":"Rolling Stone"},"beyonceknowles":{"percent":15.4,"name":"Beyonce Knowles","number":3911},"brunomars":{"name":"Bruno Mars","number":1222,"percent":4.8},"nike":{"name":"Nike","number":969,"percent":3.8},"laurenconrad":{"name":"Lauren Conrad","number":963,"percent":3.8},"lilyallen":{"name":"Lily Allen","number":843,"percent":3.3},"therock":{"name":"The Rock","number":1322,"percent":5.2},"eminem":{"name":"Eminem","number":1676,"percent":6.6},"russellbrand":{"number":1471,"percent":5.8,"name":"Russell Brand"},"paramore":{"percent":4.8,"name":"Paramore","number":1231},"adamlevine":{"name":"Adam Levine","number":1048,"percent":4.1},"jennettemccurdy":{"number":960,"percent":3.8,"name":"Jennette McCurdy"},"taylorswift":{"percent":17.8,"name":"Taylor Swift","number":4528}},"timeonnetwork":{"under6months":{"name":"< 6 months","number":509,"percent":2},"2to3years":{"name":"2-3 years","number":8711,"percent":34.2},"1to2years":{"name":"1-2 years","number":7092,"percent":27.9},"over3years":{"name":"> 3 years","number":6535,"percent":25.7},"6to12months":{"name":"6-12 months","number":2569,"percent":10.1}},"raceusonly":{"whitecaucasian":{"name":"White/caucasian","number":1702,"percent":82.5},"africanamerican":{"name":"African American","number":216,"percent":10.5},"hispanic":{"number":144,"percent":7,"name":"Hispanic"},"asian":{"percent":0,"name":"Asian","number":1}},"locationbyusstate":{"newmexico":{"number":15,"percent":0.4,"name":"New Mexico"},"southdakota":{"name":"South Dakota","number":11,"percent":0.3},"delaware":{"name":"Delaware","number":10,"percent":0.3},"texas":{"name":"Texas","number":256,"percent":6.5},"newyorkstate":{"percent":5.3,"name":"New York State","number":209},"georgia":{"name":"Georgia","number":123,"percent":3.1},"connecticut":{"name":"Connecticut","number":55,"percent":1.4},"utah":{"name":"Utah","number":40,"percent":1},"oregon":{"name":"Oregon","number":64,"percent":1.6},"iowa":{"name":"Iowa","number":36,"percent":0.9},"louisiana":{"number":28,"percent":0.7,"name":"Louisiana"},"florida":{"name":"Florida","number":244,"percent":6.2},"ohio":{"percent":4.5,"name":"Ohio","number":179},"michigan":{"name":"Michigan","number":161,"percent":4.1},"missouri":{"name":"Missouri","number":95,"percent":2.4},"newjersey":{"name":"New Jersey","number":90,"percent":2.3},"westvirginia":{"number":27,"percent":0.7,"name":"West Virginia"},"montana":{"percent":0.3,"name":"Montana","number":11},"northdakota":{"name":"North Dakota","number":10,"percent":0.3},"tennessee":{"name":"Tennessee","number":94,"percent":2.4},"washington":{"name":"Washington","number":88,"percent":2.2},"maryland":{"number":63,"percent":1.6,"name":"Maryland"},"nevada":{"percent":0.9,"name":"Nevada","number":36},"hawaii":{"name":"Hawaii","number":13,"percent":0.3},"northcarolina":{"name":"North Carolina","number":125,"percent":3.2},"virginia":{"name":"Virginia","number":91,"percent":2.3},"wisconsin":{"name":"Wisconsin","number":89,"percent":2.3},"minnesota":{"name":"Minnesota","number":73,"percent":1.8},"california":{"name":"California","number":530,"percent":13.4},"pennsylvania":{"name":"Pennsylvania","number":214,"percent":5.4},"illinois":{"name":"Illinois","number":117,"percent":3},"indiana":{"name":"Indiana","number":116,"percent":2.9},"arkansas":{"name":"Arkansas","number":41,"percent":1},"oklahoma":{"name":"Oklahoma","number":55,"percent":1.4},"arizona":{"number":50,"percent":1.3,"name":"Arizona"},"rhodeisland":{"percent":0.5,"name":"Rhode Island","number":21},"newhampshire":{"name":"New Hampshire","number":19,"percent":0.5},"dc":{"name":"DC","number":17,"percent":0.4},"idaho":{"name":"Idaho","number":9,"percent":0.2},"wyoming":{"name":"Wyoming","number":4,"percent":0.1},"colorado":{"name":"Colorado","number":97,"percent":2.5},"southcarolina":{"name":"South Carolina","number":75,"percent":1.9},"alabama":{"number":52,"percent":1.3,"name":"Alabama"},"kentucky":{"percent":0.9,"name":"Kentucky","number":36},"nebraska":{"name":"Nebraska","number":18,"percent":0.5},"alaska":{"name":"Alaska","number":6,"percent":0.2},"massachusetts":{"name":"Massachusetts","number":72,"percent":1.8},"mississippi":{"name":"Mississippi","number":23,"percent":0.6},"kansas":{"number":18,"percent":0.5,"name":"Kansas"},"maine":{"percent":0.4,"name":"Maine","number":14},"vermont":{"name":"Vermont","number":8,"percent":0.2}},"religion":{"christian":{"number":891,"percent":84.9,"name":"Christian"},"muslim":{"name":"Muslim","number":116,"percent":11},"jewish":{"name":"Jewish","number":43,"percent":4.1}},"nativelanguage":{"english":{"name":"English","number":17636,"percent":73.7},"finnish":{"name":"Finnish","number":58,"percent":0.2},"arabic":{"number":20,"percent":0.1,"name":"Arabic"},"catalan":{"percent":0.3,"name":"Catalan","number":66},"russian":{"name":"Russian","number":49,"percent":0.2},"japanese":{"number":18,"percent":0.1,"name":"Japanese"},"greek":{"percent":0,"name":"Greek","number":5},"albanian":{"name":"Albanian","number":4,"percent":0},"portuguese":{"name":"Portuguese","number":1883,"percent":7.9},"indonesian":{"name":"Indonesian","number":44,"percent":0.2},"korean":{"number":4,"percent":0,"name":"Korean"},"ukrainian":{"percent":0,"name":"Ukrainian","number":2},"italian":{"name":"Italian","number":696,"percent":2.9},"norwegian":{"number":30,"percent":0.1,"name":"Norwegian"},"polish":{"percent":0.1,"name":"Polish","number":25},"persian":{"name":"Persian","number":22,"percent":0.1},"french":{"number":490,"percent":2,"name":"French"},"german":{"name":"German","number":362,"percent":1.5},"turkish":{"name":"Turkish","number":129,"percent":0.5},"swedish":{"name":"Swedish","number":101,"percent":0.4},"thai":{"percent":0.1,"name":"Thai","number":23},"hungarian":{"name":"Hungarian","number":12,"percent":0.1},"lithuanian":{"name":"Lithuanian","number":11,"percent":0},"chinese":{"number":8,"percent":0,"name":"Chinese"},"danish":{"name":"Danish","number":81,"percent":0.3},"tagalog":{"name":"Tagalog","number":62,"percent":0.3},"dutch":{"name":"Dutch","number":57,"percent":0.2},"hebrew":{"percent":0.1,"name":"Hebrew","number":17},"czech":{"name":"Czech","number":16,"percent":0.1},"basque":{"name":"Basque","number":2,"percent":0},"spanish":{"number":1985,"percent":8.3,"name":"Spanish"}},"occupations":{"chefs":{"percent":0.5,"name":"Chefs","number":16},"eventplanners":{"name":"Event planners","number":8,"percent":0.3},"politicsgovt":{"name":"Politics/gov't.","number":1,"percent":0},"graphicdesign":{"name":"Graphic design","number":94,"percent":3.1},"stylists":{"name":"Stylists","number":84,"percent":2.7},"webdevelopers":{"number":43,"percent":1.4,"name":"Web developers"},"nurses":{"name":"Nurses","number":30,"percent":1},"lawyers":{"name":"Lawyers","number":18,"percent":0.6},"realtors":{"name":"Realtors","number":1,"percent":0},"military":{"percent":0.7,"name":"Military","number":21},"programmers":{"name":"Programmers","number":17,"percent":0.6},"doctors":{"name":"Doctors","number":10,"percent":0.3},"musicians":{"name":"Musicians","number":461,"percent":15},"actors":{"name":"Actors","number":107,"percent":3.5},"models":{"number":89,"percent":2.9,"name":"Models"},"entrepreneurs":{"percent":2.1,"name":"Entrepreneurs","number":65},"architects":{"name":"Architects","number":22,"percent":0.7},"humanresources":{"name":"Human resources","number":2,"percent":0.1},"authorswriters":{"name":"Authors/writers","number":147,"percent":4.8},"designers":{"name":"Designers","number":118,"percent":3.8},"djs":{"name":"DJs","number":27,"percent":0.9},"engineers":{"name":"Engineers","number":22,"percent":0.7},"scientists":{"name":"Scientists","number":12,"percent":0.4},"journalists":{"number":136,"percent":4.4,"name":"Journalists"},"mediaproduction":{"percent":1.3,"name":"Media production","number":39},"consultants":{"name":"Consultants","number":26,"percent":0.8},"tvradiohosts":{"name":"TV/radio hosts","number":7,"percent":0.2},"pilots":{"name":"Pilots","number":1,"percent":0},"secretarialadmin":{"number":5,"percent":0.2,"name":"Secretarial/admin"},"photographers":{"name":"Photographers","number":188,"percent":6.1},"salesmarketing":{"percent":2.5,"name":"Sales/marketing","number":77},"publicservice":{"name":"Public service","number":9,"percent":0.3},"agentspromoters":{"name":"Agents/promoters","number":8,"percent":0.3},"manufacturing":{"name":"Manufacturing","number":7,"percent":0.2},"artists":{"name":"Artists","number":475,"percent":15.5},"dancers":{"name":"Dancers","number":101,"percent":3.3},"healthworkers":{"number":74,"percent":2.4,"name":"Health workers"},"investors":{"percent":0.4,"name":"Investors","number":12},"construction":{"name":"Construction","number":5,"percent":0.2},"personaltrainers":{"number":13,"percent":0.4,"name":"Personal trainers"},"financebanking":{"percent":0.1,"name":"Finance/banking","number":4},"accountants":{"name":"Accountants","number":3,"percent":0.1},"librarians":{"name":"Librarians","number":3,"percent":0.1},"churchleaders":{"name":"Church leaders","number":3,"percent":0.1},"itprofessionals":{"name":"IT professionals","number":3,"percent":0.1},"students":{"name":"Students","number":266,"percent":8.7},"teachers":{"name":"Teachers","number":87,"percent":2.8},"seniormanagers":{"name":"Senior managers","number":68,"percent":2.2},"comedians":{"name":"Comedians","number":20,"percent":0.7},"hospitality":{"name":"Hospitality","number":15,"percent":0.5}},"gender":{"female":{"number":17424,"percent":83.5,"name":"Female"},"male":{"name":"Male","number":3432,"percent":16.5}},"familystatus":{"married":{"name":"Married","number":457,"percent":14.3},"single":{"number":2743,"percent":85.7,"name":"Single"},"parents":{"name":"Parents","number":1457,"percent":5.7}},"personalincome":{"20000to29999":{"name":"$20,000 - $29,999","number":543,"percent":10.4},"30000to39999":{"number":224,"percent":4.3,"name":"$30,000 - $39,999"},"40000to49999":{"name":"$40,000 - $49,999","number":78,"percent":1.5},"50000to74999":{"percent":0.8,"name":"$50,000 - $74,999","number":41},"75000to99999":{"name":"$75,000 - $99,999","number":1,"percent":0},"under10000":{"name":"Under $10,000","number":2843,"percent":54.5},"10000to19999":{"name":"$10,000 - $19,999","number":1484,"percent":28.5}},"postingfrequency":{"1to5postsperday":{"number":1727,"percent":6.8,"name":"1-5 posts/day"},"over5postsperday":{"percent":0.1,"name":"> 5 posts/day","number":16},"1to7postsperweek":{"name":"1-7 posts/week","number":13751,"percent":54},"1to4postspermonth":{"name":"1-4 posts/month","number":7332,"percent":28.8},"under1postpermonth":{"name":"< 1 post/month","number":2518,"percent":9.9}},"networksettings":{"geoenabled":{"name":"Geo-enabled","number":10960,"percent":43.1},"websiteset":{"number":5554,"percent":21.8,"name":"Website set"},"protected":{"percent":3.2,"name":"Protected","number":810}},"locationbycountry":{"qatar":{"name":"Qatar","number":1,"percent":0},"mauritius":{"name":"Mauritius","number":1,"percent":0},"aruba":{"number":1,"percent":0,"name":"Aruba"},"yemen":{"percent":0,"name":"Yemen","number":1},"peru":{"name":"Peru","number":16,"percent":0.1},"paraguay":{"name":"Paraguay","number":5,"percent":0},"switzerland":{"name":"Switzerland","number":57,"percent":0.5},"ecuador":{"name":"Ecuador","number":12,"percent":0.1},"jamaica":{"name":"Jamaica","number":8,"percent":0.1},"kenya":{"name":"Kenya","number":7,"percent":0.1},"bolivia":{"number":2,"percent":0,"name":"Bolivia"},"sudan":{"percent":0,"name":"Sudan","number":1},"unitedkingdom":{"name":"United Kingdom","number":1720,"percent":14.2},"france":{"name":"France","number":231,"percent":1.9},"domrepublic":{"number":8,"percent":0.1,"name":"Dom. Republic"},"isleofman":{"percent":0,"name":"Isle of Man","number":2},"panama":{"name":"Panama","number":4,"percent":0},"kuwait":{"name":"Kuwait","number":2,"percent":0},"russia":{"name":"Russia","number":30,"percent":0.2},"malaysia":{"number":20,"percent":0.2,"name":"Malaysia"},"japan":{"name":"Japan","number":19,"percent":0.2},"cyprus":{"percent":0,"name":"Cyprus","number":2},"italy":{"name":"Italy","number":402,"percent":3.3},"argentina":{"name":"Argentina","number":128,"percent":1.1},"latvia":{"name":"Latvia","number":11,"percent":0.1},"romania":{"name":"Romania","number":6,"percent":0},"saudiarabia":{"name":"Saudi Arabia","number":4,"percent":0},"pakistan":{"name":"Pakistan","number":3,"percent":0},"southkorea":{"name":"South Korea","number":2,"percent":0},"costarica":{"number":1,"percent":0,"name":"Costa Rica"},"ireland":{"percent":0.7,"name":"Ireland","number":79},"southafrica":{"name":"South Africa","number":68,"percent":0.6},"elsalvador":{"name":"El Salvador","number":1,"percent":0},"egypt":{"name":"Egypt","number":41,"percent":0.3},"indonesia":{"name":"Indonesia","number":40,"percent":0.3},"lebanon":{"name":"Lebanon","number":17,"percent":0.1},"nigeria":{"name":"Nigeria","number":6,"percent":0},"czechrepublic":{"name":"Czech Republic","number":5,"percent":0},"belarus":{"number":1,"percent":0,"name":"Belarus"},"australia":{"name":"Australia","number":294,"percent":2.4},"sweden":{"percent":0.4,"name":"Sweden","number":53},"ghana":{"name":"Ghana","number":1,"percent":0},"india":{"name":"India","number":25,"percent":0.2},"china":{"name":"China","number":6,"percent":0},"brunei":{"name":"Brunei","number":1,"percent":0},"maldives":{"name":"Maldives","number":1,"percent":0},"spain":{"name":"Spain","number":430,"percent":3.6},"portugal":{"name":"Portugal","number":26,"percent":0.2},"philippines":{"name":"Philippines","number":20,"percent":0.2},"guernsey":{"name":"Guernsey","number":1,"percent":0},"vietnam":{"name":"Vietnam","number":1,"percent":0},"denmark":{"number":82,"percent":0.7,"name":"Denmark"},"greece":{"percent":0.3,"name":"Greece","number":38},"colombia":{"name":"Colombia","number":64,"percent":0.5},"newzealand":{"name":"New Zealand","number":40,"percent":0.3},"finland":{"name":"Finland","number":28,"percent":0.2},"uruguay":{"number":14,"percent":0.1,"name":"Uruguay"},"estonia":{"name":"Estonia","number":3,"percent":0},"unitedstates":{"name":"United States","number":5206,"percent":43.1},"mexico":{"percent":1.5,"name":"Mexico","number":181},"turkey":{"name":"Turkey","number":105,"percent":0.9},"thailand":{"number":24,"percent":0.2,"name":"Thailand"},"hungary":{"percent":0.2,"name":"Hungary","number":20},"serbia":{"name":"Serbia","number":9,"percent":0.1},"croatia":{"name":"Croatia","number":4,"percent":0},"slovenia":{"name":"Slovenia","number":2,"percent":0},"brazil":{"name":"Brazil","number":1197,"percent":9.9},"germany":{"number":201,"percent":1.7,"name":"Germany"},"suriname":{"percent":0,"name":"Suriname","number":1},"slovakia":{"name":"Slovakia","number":2,"percent":0},"cuba":{"name":"Cuba","number":1,"percent":0},"belgium":{"name":"Belgium","number":14,"percent":0.1},"venezuela":{"name":"Venezuela","number":71,"percent":0.6},"puertorico":{"name":"Puerto Rico","number":38,"percent":0.3},"poland":{"name":"Poland","number":10,"percent":0.1},"ukraine":{"name":"Ukraine","number":5,"percent":0},"bermuda":{"name":"Bermuda","number":2,"percent":0},"canada":{"name":"Canada","number":462,"percent":3.8},"israel":{"number":19,"percent":0.2,"name":"Israel"},"netherlands":{"percent":1.2,"name":"Netherlands","number":141},"jordan":{"name":"Jordan","number":4,"percent":0},"lithuania":{"name":"Lithuania","number":2,"percent":0},"chile":{"name":"Chile","number":151,"percent":1.2},"austria":{"name":"Austria","number":15,"percent":0.1},"uae":{"name":"UAE","number":11,"percent":0.1},"iran":{"name":"Iran","number":11,"percent":0.1},"taiwan":{"number":3,"percent":0,"name":"Taiwan"},"bahrain":{"name":"Bahrain","number":3,"percent":0},"zimbabwe":{"name":"Zimbabwe","number":1,"percent":0},"greenland":{"name":"Greenland","number":1,"percent":0},"norway":{"percent":0.4,"name":"Norway","number":48},"guatemala":{"name":"Guatemala","number":22,"percent":0.2}},"brands":{"americanapparel":{"name":"American Apparel","number":1280,"percent":5},"netflix":{"percent":5,"name":"Netflix","number":1272},"bbc":{"name":"BBC","number":1043,"percent":4.1},"pacsun":{"number":862,"percent":3.4,"name":"PacSun"},"ikea":{"name":"Ikea","number":573,"percent":2.3},"toms":{"percent":2,"name":"TOMS","number":514},"maybelline":{"name":"Maybelline","number":446,"percent":1.8},"handm":{"number":1803,"percent":7.1,"name":"H & M "},"omgfacts":{"percent":1.7,"name":"OMG Facts","number":420},"urbanoutfitters":{"name":"Urban Outfitters","number":3088,"percent":12.1},"anthropologie":{"name":"Anthropologie","number":718,"percent":2.8},"pizzahut":{"name":"Pizza Hut","number":439,"percent":1.7},"fallout":{"name":"Fallout","number":398,"percent":1.6},"modcloth":{"name":"Modcloth","number":342,"percent":1.3},"victoriassecret":{"name":"Victoria's Secret","number":3095,"percent":12.2},"gopro":{"name":"GoPro","number":1305,"percent":5.1},"billabong":{"name":"Billabong","number":701,"percent":2.8},"vine":{"number":672,"percent":2.6,"name":"Vine"},"inked":{"percent":2.3,"name":"Inked ","number":581},"alexandermcqueen":{"name":"Alexander McQueen","number":385,"percent":1.5},"thrasher":{"name":"Thrasher ","number":370,"percent":1.5},"topshop":{"name":"Topshop","number":1886,"percent":7.4},"walmart":{"name":"Walmart","number":840,"percent":3.3},"applemac":{"number":703,"percent":2.8,"name":"Apple Mac"},"eonline":{"name":"E! Online","number":444,"percent":1.7},"mango":{"name":"Mango","number":373,"percent":1.5},"drmartens":{"name":"Dr. Martens","number":1536,"percent":6},"9gag":{"percent":7.5,"name":"9GAG","number":1914},"converse":{"name":"Converse","number":1205,"percent":4.7},"etsy":{"name":"Etsy","number":963,"percent":3.8},"marcjacobs":{"number":536,"percent":2.1,"name":"Marc Jacobs"},"teenvogue":{"name":"Teen Vogue","number":527,"percent":2.1},"americaneagle":{"name":"American Eagle","number":342,"percent":1.3},"vans":{"name":"Vans","number":2159,"percent":8.5},"asos":{"name":"Asos","number":1361,"percent":5.3},"benefitcosmetics":{"name":"Benefit Cosmetics","number":965,"percent":3.8},"elle":{"percent":2.6,"name":"Elle","number":657},"cocacola":{"name":"Coca Cola","number":635,"percent":2.5},"target":{"name":"Target","number":613,"percent":2.4},"canon":{"name":"Canon","number":495,"percent":1.9},"versace":{"name":"Versace","number":489,"percent":1.9},"mtv":{"name":"MTV","number":1522,"percent":6},"riverisland":{"name":"River Island","number":415,"percent":1.6},"givenchy":{"number":398,"percent":1.6,"name":"Givenchy"},"christianlouboutin":{"percent":1.9,"name":"Christian Louboutin","number":478},"rollingstone":{"name":"Rolling Stone","number":905,"percent":3.6},"instagram":{"name":"Instagram","number":4967,"percent":19.5},"nutella":{"name":"Nutella","number":675,"percent":2.7},"prada":{"name":"Prada","number":483,"percent":1.9},"marvel":{"name":"Marvel","number":744,"percent":2.9},"iphone":{"number":817,"percent":3.2,"name":"iPhone"},"christiandior":{"name":"Christian Dior","number":809,"percent":3.2},"louisvuitton":{"percent":2.9,"name":"Louis Vuitton","number":747},"facebook":{"name":"Facebook","number":711,"percent":2.8},"redbull":{"name":"Redbull","number":593,"percent":2.3},"cnn":{"name":"CNN","number":518,"percent":2},"burgerking":{"name":"Burger King","number":379,"percent":1.5},"nike":{"name":"Nike","number":2351,"percent":9.2},"dolceandgabbana":{"name":"Dolce & Gabbana","number":718,"percent":2.8},"cosmopolitan":{"name":"Cosmopolitan","number":554,"percent":2.2},"benandjerrys":{"name":"Ben & Jerry's","number":455,"percent":1.8},"rayban":{"name":"Rayban","number":355,"percent":1.4},"forever21":{"name":"Forever 21","number":2187,"percent":8.6},"starbucks":{"name":"Starbucks","number":3248,"percent":12.8},"freepeople":{"number":2817,"percent":11.1,"name":"Free People"},"disney":{"percent":8.2,"name":"Disney","number":2093},"tumblr":{"name":"Tumblr","number":1493,"percent":5.9},"adidas":{"name":"Adidas","number":1250,"percent":4.9},"aeropostale":{"name":"Aeropostale","number":545,"percent":2.1},"nytimes":{"name":"NY Times","number":406,"percent":1.6},"nationalgeographic":{"name":"National Geographic","number":3731,"percent":14.7},"smosh":{"name":"Smosh","number":358,"percent":1.4},"youtube":{"name":"Youtube","number":1640,"percent":6.4},"tacobell":{"name":"Taco Bell","number":955,"percent":3.8},"michaelkors":{"number":552,"percent":2.2,"name":"Michael Kors"},"calvinklein":{"percent":2.1,"name":"Calvin Klein","number":546},"abercrombieandfitch":{"name":"Abercrombie & Fitch","number":476,"percent":1.9},"volkswagen":{"name":"Volkswagen","number":398,"percent":1.6},"samsung":{"name":"Samsung","number":339,"percent":1.3},"mcdonalds":{"name":"McDonald's","number":1811,"percent":7.1},"hollister":{"name":"Hollister","number":573,"percent":2.3},"wholefoods":{"name":"Whole Foods","number":462,"percent":1.8},"ulta":{"name":"Ulta","number":371,"percent":1.5},"funnyordie":{"number":354,"percent":1.4,"name":"Funny Or Die"},"hottopic":{"percent":2.7,"name":"Hot Topic","number":689},"uberfacts":{"name":"UberFacts","number":1087,"percent":4.3},"google":{"number":784,"percent":3.1,"name":"Google"},"burberry":{"percent":2.8,"name":"Burberry","number":707},"subway":{"name":"Subway","number":485,"percent":1.9},"kfc":{"name":"KFC","number":395,"percent":1.6},"sephora":{"name":"Sephora","number":1161,"percent":4.6},"gucci":{"name":"Gucci","number":458,"percent":1.8},"lego":{"number":346,"percent":1.4,"name":"Lego"},"zara":{"percent":4.3,"name":"Zara","number":1096},"chanel":{"name":"Chanel","number":1142,"percent":4.5},"primark":{"number":796,"percent":3.1,"name":"Primark"},"playboy":{"name":"Playboy","number":421,"percent":1.7},"amcnetworks":{"percent":1.4,"name":"AMC Networks","number":365},"armani":{"name":"Armani","number":357,"percent":1.4},"vogue":{"name":"Vogue","number":1722,"percent":6.8}},"numberoffollowers":{"101to1000followers":{"name":"101-1,000 followers","number":19821,"percent":77.9},"10to100followers":{"name":"10-100 followers","number":2938,"percent":11.5},"over1000followers":{"number":2598,"percent":10.2,"name":"> 1,000 followers"},"under10followers":{"percent":0.2,"name":"< 10 followers","number":59}},"agecensus":{"age60andover":{"name":"Age 60 and over","number":8,"percent":0.1},"age17to19":{"number":3598,"percent":50.2,"name":"Age 17 to 19"},"age20to24":{"percent":32.3,"name":"Age 20 to 24","number":2313},"age25to29":{"name":"Age 25 to 29","number":549,"percent":7.7},"age35to39":{"number":49,"percent":0.7,"name":"Age 35 to 39"},"age50to59":{"percent":0.1,"name":"Age 50 to 59","number":6},"age16andunder":{"name":"Age 16 and under","number":342,"percent":4.8},"age30to34":{"name":"Age 30 to 34","number":246,"percent":3.4},"age40to49":{"name":"Age 40 to 49","number":50,"percent":0.7}}},"taxonomy_version":"4","analysis_id":3216105,"__v":0,"handle":"elise.buch","request_id":4214504,"analysis_date":"2016-03-07 21:00:47","network":"instagram","status":"complete","error_details":"","analysis_name":"","number_processed":null,"number_submitted":null,"errorCode":null,"errorMessage":"","created":"2016-03-23T19:51:23.000Z","updated":"2017-03-25T03:37:18.318Z","deleted":false}}
